{
"meta":{"test_sets":[],"test_metrics":[],"learn_metrics":[{"best_value":"Min","name":"Logloss"}],"launch_mode":"Train","parameters":"","iteration_count":1000,"learn_sets":["learn"],"name":"experiment"},
"iterations":[
{"learn":[0.6873382419],"iteration":0,"passed_time":0.002079377733,"remaining_time":2.077298355},
{"learn":[0.6820748386],"iteration":1,"passed_time":0.004534523117,"remaining_time":2.262727035},
{"learn":[0.6762700179],"iteration":2,"passed_time":0.006905858578,"remaining_time":2.295047001},
{"learn":[0.6712744108],"iteration":3,"passed_time":0.009513011086,"remaining_time":2.36873976},
{"learn":[0.6666738617],"iteration":4,"passed_time":0.01111266894,"remaining_time":2.211421119},
{"learn":[0.661749832],"iteration":5,"passed_time":0.01421717549,"remaining_time":2.355312074},
{"learn":[0.6564972967],"iteration":6,"passed_time":0.01688680826,"remaining_time":2.395514372},
{"learn":[0.6531588238],"iteration":7,"passed_time":0.01914346834,"remaining_time":2.373790074},
{"learn":[0.6478125589],"iteration":8,"passed_time":0.02136340504,"remaining_time":2.352348266},
{"learn":[0.6427996314],"iteration":9,"passed_time":0.0236439239,"remaining_time":2.340748466},
{"learn":[0.6385261992],"iteration":10,"passed_time":0.02526275236,"remaining_time":2.271351098},
{"learn":[0.6349020273],"iteration":11,"passed_time":0.02682140227,"remaining_time":2.208295454},
{"learn":[0.6307966531],"iteration":12,"passed_time":0.02923585858,"remaining_time":2.21967634},
{"learn":[0.6260651212],"iteration":13,"passed_time":0.03195698916,"remaining_time":2.250685094},
{"learn":[0.6215356718],"iteration":14,"passed_time":0.03418334515,"remaining_time":2.244706332},
{"learn":[0.6179055527],"iteration":15,"passed_time":0.03574328312,"remaining_time":2.198211912},
{"learn":[0.6140013356],"iteration":16,"passed_time":0.03807465619,"remaining_time":2.201611002},
{"learn":[0.6108323825],"iteration":17,"passed_time":0.03966920462,"remaining_time":2.164175497},
{"learn":[0.6076338025],"iteration":18,"passed_time":0.0411983258,"remaining_time":2.127134611},
{"learn":[0.6044344757],"iteration":19,"passed_time":0.04419660778,"remaining_time":2.165633781},
{"learn":[0.6008394377],"iteration":20,"passed_time":0.04670587575,"remaining_time":2.177383446},
{"learn":[0.5970214867],"iteration":21,"passed_time":0.04905572631,"remaining_time":2.180750015},
{"learn":[0.5935386855],"iteration":22,"passed_time":0.05142740162,"remaining_time":2.184546582},
{"learn":[0.5904735837],"iteration":23,"passed_time":0.05375153641,"remaining_time":2.185895814},
{"learn":[0.5883647412],"iteration":24,"passed_time":0.0554319523,"remaining_time":2.16184614},
{"learn":[0.5846907592],"iteration":25,"passed_time":0.05785683555,"remaining_time":2.16740607},
{"learn":[0.5811348053],"iteration":26,"passed_time":0.06055235526,"remaining_time":2.182127469},
{"learn":[0.5779786882],"iteration":27,"passed_time":0.06289225214,"remaining_time":2.18325961},
{"learn":[0.5746537164],"iteration":28,"passed_time":0.06526643726,"remaining_time":2.185300365},
{"learn":[0.5715215187],"iteration":29,"passed_time":0.06742131676,"remaining_time":2.179955909},
{"learn":[0.5693212399],"iteration":30,"passed_time":0.0693354972,"remaining_time":2.167293445},
{"learn":[0.5660298364],"iteration":31,"passed_time":0.07155861166,"remaining_time":2.164648003},
{"learn":[0.5629298823],"iteration":32,"passed_time":0.07377680634,"remaining_time":2.161883992},
{"learn":[0.5599015488],"iteration":33,"passed_time":0.07667172432,"remaining_time":2.178378991},
{"learn":[0.5572924064],"iteration":34,"passed_time":0.07877802363,"remaining_time":2.172022652},
{"learn":[0.5541758652],"iteration":35,"passed_time":0.08095971731,"remaining_time":2.167921319},
{"learn":[0.5516466303],"iteration":36,"passed_time":0.08263101612,"remaining_time":2.15063969},
{"learn":[0.5488852114],"iteration":37,"passed_time":0.08477910963,"remaining_time":2.146250091},
{"learn":[0.5466444177],"iteration":38,"passed_time":0.08624125956,"remaining_time":2.125073088},
{"learn":[0.5452146027],"iteration":39,"passed_time":0.08725290117,"remaining_time":2.094069628},
{"learn":[0.5432804722],"iteration":40,"passed_time":0.08863706553,"remaining_time":2.073242582},
{"learn":[0.5404827645],"iteration":41,"passed_time":0.09078738691,"remaining_time":2.070817063},
{"learn":[0.5382538644],"iteration":42,"passed_time":0.09248227683,"remaining_time":2.058268347},
{"learn":[0.5358217336],"iteration":43,"passed_time":0.09450638741,"remaining_time":2.053366054},
{"learn":[0.5333824902],"iteration":44,"passed_time":0.09650630691,"remaining_time":2.048078291},
{"learn":[0.5316026782],"iteration":45,"passed_time":0.09854512144,"remaining_time":2.043740127},
{"learn":[0.5290265589],"iteration":46,"passed_time":0.1005974299,"remaining_time":2.039773419},
{"learn":[0.5270883172],"iteration":47,"passed_time":0.102026249,"remaining_time":2.023520606},
{"learn":[0.5254245626],"iteration":48,"passed_time":0.1034429965,"remaining_time":2.007638566},
{"learn":[0.5229499917],"iteration":49,"passed_time":0.1056203973,"remaining_time":2.006787548},
{"learn":[0.5210104907],"iteration":50,"passed_time":0.1081694187,"remaining_time":2.012799575},
{"learn":[0.5184621021],"iteration":51,"passed_time":0.1103480328,"remaining_time":2.011729521},
{"learn":[0.5163518193],"iteration":52,"passed_time":0.1125181977,"remaining_time":2.010466665},
{"learn":[0.5143023999],"iteration":53,"passed_time":0.1146006416,"remaining_time":2.007633463},
{"learn":[0.5121552032],"iteration":54,"passed_time":0.1168553969,"remaining_time":2.007788183},
{"learn":[0.5102186926],"iteration":55,"passed_time":0.1190161536,"remaining_time":2.006272304},
{"learn":[0.5084833998],"iteration":56,"passed_time":0.1207313302,"remaining_time":1.997362182},
{"learn":[0.5069354474],"iteration":57,"passed_time":0.1225883311,"remaining_time":1.991003584},
{"learn":[0.5046021605],"iteration":58,"passed_time":0.1249680259,"remaining_time":1.993134108},
{"learn":[0.5029288571],"iteration":59,"passed_time":0.127025505,"remaining_time":1.990066246},
{"learn":[0.5015471693],"iteration":60,"passed_time":0.1292016395,"remaining_time":1.988858025},
{"learn":[0.4996727173],"iteration":61,"passed_time":0.131655804,"remaining_time":1.991824905},
{"learn":[0.4980951981],"iteration":62,"passed_time":0.1339483835,"remaining_time":1.992216435},
{"learn":[0.497251344],"iteration":63,"passed_time":0.1350936488,"remaining_time":1.975744613},
{"learn":[0.4964238073],"iteration":64,"passed_time":0.1362208594,"remaining_time":1.95948467},
{"learn":[0.4946820024],"iteration":65,"passed_time":0.13871082,"remaining_time":1.962968271},
{"learn":[0.4929861622],"iteration":66,"passed_time":0.1414302581,"remaining_time":1.969469116},
{"learn":[0.4912626021],"iteration":67,"passed_time":0.1437459127,"remaining_time":1.970164568},
{"learn":[0.489452394],"iteration":68,"passed_time":0.1460747634,"remaining_time":1.970950793},
{"learn":[0.4880493144],"iteration":69,"passed_time":0.1483727905,"remaining_time":1.971238503},
{"learn":[0.4872559567],"iteration":70,"passed_time":0.149692251,"remaining_time":1.958649312},
{"learn":[0.4860988361],"iteration":71,"passed_time":0.1511411855,"remaining_time":1.948041947},
{"learn":[0.4851551462],"iteration":72,"passed_time":0.1525806338,"remaining_time":1.937565035},
{"learn":[0.4835089861],"iteration":73,"passed_time":0.1553735019,"remaining_time":1.944268415},
{"learn":[0.4820483716],"iteration":74,"passed_time":0.1576828547,"remaining_time":1.944755208},
{"learn":[0.48098414],"iteration":75,"passed_time":0.1591440531,"remaining_time":1.934856645},
{"learn":[0.479568628],"iteration":76,"passed_time":0.1613421356,"remaining_time":1.934010275},
{"learn":[0.478023614],"iteration":77,"passed_time":0.1633642692,"remaining_time":1.931049439},
{"learn":[0.4765862028],"iteration":78,"passed_time":0.1652683693,"remaining_time":1.926736305},
{"learn":[0.4755641485],"iteration":79,"passed_time":0.1666735487,"remaining_time":1.91674581},
{"learn":[0.474001497],"iteration":80,"passed_time":0.1686766996,"remaining_time":1.913751691},
{"learn":[0.472560851],"iteration":81,"passed_time":0.1716086716,"remaining_time":1.921180006},
{"learn":[0.4711494342],"iteration":82,"passed_time":0.174012998,"remaining_time":1.922529147},
{"learn":[0.4703638949],"iteration":83,"passed_time":0.1754957241,"remaining_time":1.913739086},
{"learn":[0.4693379964],"iteration":84,"passed_time":0.1771916872,"remaining_time":1.907416398},
{"learn":[0.4688119306],"iteration":85,"passed_time":0.178454193,"remaining_time":1.896594563},
{"learn":[0.4680159829],"iteration":86,"passed_time":0.1803097859,"remaining_time":1.892216489},
{"learn":[0.4666804976],"iteration":87,"passed_time":0.182499218,"remaining_time":1.891355532},
{"learn":[0.46542745],"iteration":88,"passed_time":0.1844952548,"remaining_time":1.888485137},
{"learn":[0.4643099777],"iteration":89,"passed_time":0.1869620246,"remaining_time":1.890393804},
{"learn":[0.4631560363],"iteration":90,"passed_time":0.1890587302,"remaining_time":1.888509734},
{"learn":[0.4620544096],"iteration":91,"passed_time":0.1910017496,"remaining_time":1.885104225},
{"learn":[0.4615321833],"iteration":92,"passed_time":0.1923195788,"remaining_time":1.875632882},
{"learn":[0.4603192877],"iteration":93,"passed_time":0.1944199598,"remaining_time":1.873877485},
{"learn":[0.4590585654],"iteration":94,"passed_time":0.1964670498,"remaining_time":1.871607158},
{"learn":[0.4578636578],"iteration":95,"passed_time":0.1985021671,"remaining_time":1.86922874},
{"learn":[0.4569435007],"iteration":96,"passed_time":0.2004926758,"remaining_time":1.866442127},
{"learn":[0.4558214508],"iteration":97,"passed_time":0.2031792186,"remaining_time":1.870078114},
{"learn":[0.454886633],"iteration":98,"passed_time":0.2049312075,"remaining_time":1.865080989},
{"learn":[0.4537578124],"iteration":99,"passed_time":0.2069842535,"remaining_time":1.862858282},
{"learn":[0.4527604597],"iteration":100,"passed_time":0.2090248445,"remaining_time":1.860528071},
{"learn":[0.4518338278],"iteration":101,"passed_time":0.2110288942,"remaining_time":1.857881833},
{"learn":[0.4507009446],"iteration":102,"passed_time":0.2129542341,"remaining_time":1.854562602},
{"learn":[0.4503414608],"iteration":103,"passed_time":0.213927532,"remaining_time":1.843067968},
{"learn":[0.4494986247],"iteration":104,"passed_time":0.2158797507,"remaining_time":1.840117875},
{"learn":[0.4483581299],"iteration":105,"passed_time":0.2185468971,"remaining_time":1.843216283},
{"learn":[0.4473888161],"iteration":106,"passed_time":0.2204711714,"remaining_time":1.840007066},
{"learn":[0.4463998231],"iteration":107,"passed_time":0.2226139197,"remaining_time":1.838626077},
{"learn":[0.4455385837],"iteration":108,"passed_time":0.2247129891,"remaining_time":1.836874067},
{"learn":[0.4448040599],"iteration":109,"passed_time":0.2267786656,"remaining_time":1.834845567},
{"learn":[0.4438789181],"iteration":110,"passed_time":0.22875803,"remaining_time":1.832125123},
{"learn":[0.4427892045],"iteration":111,"passed_time":0.2307750139,"remaining_time":1.829716182},
{"learn":[0.4419258719],"iteration":112,"passed_time":0.2330398806,"remaining_time":1.829259948},
{"learn":[0.4410570955],"iteration":113,"passed_time":0.2355768715,"remaining_time":1.830886914},
{"learn":[0.440549201],"iteration":114,"passed_time":0.2369563569,"remaining_time":1.823533703},
{"learn":[0.440268489],"iteration":115,"passed_time":0.2381413672,"remaining_time":1.814801454},
{"learn":[0.4394958158],"iteration":116,"passed_time":0.2401936379,"remaining_time":1.812743438},
{"learn":[0.4385407022],"iteration":117,"passed_time":0.2423573777,"remaining_time":1.811518705},
{"learn":[0.4379127455],"iteration":118,"passed_time":0.2443578544,"remaining_time":1.809069493},
{"learn":[0.4373721737],"iteration":119,"passed_time":0.2463248752,"remaining_time":1.806382418},
{"learn":[0.4367426605],"iteration":120,"passed_time":0.2486085937,"remaining_time":1.806007883},
{"learn":[0.4361699328],"iteration":121,"passed_time":0.2511255103,"remaining_time":1.807280312},
{"learn":[0.4353373015],"iteration":122,"passed_time":0.2533075278,"remaining_time":1.806103268},
{"learn":[0.4345916682],"iteration":123,"passed_time":0.2553334543,"remaining_time":1.803807306},
{"learn":[0.4339923597],"iteration":124,"passed_time":0.256944374,"remaining_time":1.798610618},
{"learn":[0.4332234457],"iteration":125,"passed_time":0.2592210438,"remaining_time":1.798088828},
{"learn":[0.4330014066],"iteration":126,"passed_time":0.260279662,"remaining_time":1.789166496},
{"learn":[0.4325773577],"iteration":127,"passed_time":0.2624024979,"remaining_time":1.787617017},
{"learn":[0.4317877753],"iteration":128,"passed_time":0.264957212,"remaining_time":1.788974664},
{"learn":[0.4310749857],"iteration":129,"passed_time":0.2675100195,"remaining_time":1.790259361},
{"learn":[0.4307578192],"iteration":130,"passed_time":0.2689034277,"remaining_time":1.783794493},
{"learn":[0.4298896319],"iteration":131,"passed_time":0.2710201229,"remaining_time":1.782162626},
{"learn":[0.4291717947],"iteration":132,"passed_time":0.2732676315,"remaining_time":1.781376214},
{"learn":[0.4289797472],"iteration":133,"passed_time":0.2744844621,"remaining_time":1.773907046},
{"learn":[0.4282192866],"iteration":134,"passed_time":0.2765445719,"remaining_time":1.771933739},
{"learn":[0.4279077353],"iteration":135,"passed_time":0.278096127,"remaining_time":1.766728337},
{"learn":[0.4272481276],"iteration":136,"passed_time":0.2805004417,"remaining_time":1.766948038},
{"learn":[0.4264465469],"iteration":137,"passed_time":0.2826962108,"remaining_time":1.765827056},
{"learn":[0.4258421015],"iteration":138,"passed_time":0.2846690619,"remaining_time":1.763309801},
{"learn":[0.4250749309],"iteration":139,"passed_time":0.2867118203,"remaining_time":1.761229753},
{"learn":[0.4247066208],"iteration":140,"passed_time":0.2887382393,"remaining_time":1.759050692},
{"learn":[0.4238582792],"iteration":141,"passed_time":0.2907126612,"remaining_time":1.756559601},
{"learn":[0.4236856836],"iteration":142,"passed_time":0.2918853683,"remaining_time":1.749271053},
{"learn":[0.423281176],"iteration":143,"passed_time":0.2937282124,"remaining_time":1.74605104},
{"learn":[0.4231794759],"iteration":144,"passed_time":0.2949923377,"remaining_time":1.739437577},
{"learn":[0.4227384227],"iteration":145,"passed_time":0.2977812996,"remaining_time":1.741816643},
{"learn":[0.4225857762],"iteration":146,"passed_time":0.2988440085,"remaining_time":1.734108431},
{"learn":[0.4220567525],"iteration":147,"passed_time":0.3008085028,"remaining_time":1.731681381},
{"learn":[0.4213757366],"iteration":148,"passed_time":0.3028174001,"remaining_time":1.729514144},
{"learn":[0.4207350739],"iteration":149,"passed_time":0.304821073,"remaining_time":1.727319414},
{"learn":[0.4204566178],"iteration":150,"passed_time":0.3061145718,"remaining_time":1.721134248},
{"learn":[0.4200576268],"iteration":151,"passed_time":0.308205104,"remaining_time":1.719460054},
{"learn":[0.4196034795],"iteration":152,"passed_time":0.3103467127,"remaining_time":1.718063174},
{"learn":[0.4193708472],"iteration":153,"passed_time":0.31230476,"remaining_time":1.715648227},
{"learn":[0.4187353064],"iteration":154,"passed_time":0.3146358797,"remaining_time":1.715273021},
{"learn":[0.4182476734],"iteration":155,"passed_time":0.3166097964,"remaining_time":1.712940181},
{"learn":[0.4175754979],"iteration":156,"passed_time":0.3186463999,"remaining_time":1.710948504},
{"learn":[0.4170125606],"iteration":157,"passed_time":0.3204936418,"remaining_time":1.707947129},
{"learn":[0.4167397094],"iteration":158,"passed_time":0.3224525282,"remaining_time":1.705550794},
{"learn":[0.4164253712],"iteration":159,"passed_time":0.3245285192,"remaining_time":1.703774726},
{"learn":[0.4158393552],"iteration":160,"passed_time":0.3265015297,"remaining_time":1.701458282},
{"learn":[0.4155110946],"iteration":161,"passed_time":0.3295022695,"remaining_time":1.704462357},
{"learn":[0.414942384],"iteration":162,"passed_time":0.3317171127,"remaining_time":1.703357198},
{"learn":[0.4145342171],"iteration":163,"passed_time":0.3337761526,"remaining_time":1.70144429},
{"learn":[0.4140431656],"iteration":164,"passed_time":0.3360155494,"remaining_time":1.700442326},
{"learn":[0.4134392658],"iteration":165,"passed_time":0.3382301887,"remaining_time":1.699301069},
{"learn":[0.4129973331],"iteration":166,"passed_time":0.3405480461,"remaining_time":1.698661811},
{"learn":[0.4125189652],"iteration":167,"passed_time":0.3427753494,"remaining_time":1.697554111},
{"learn":[0.412233037],"iteration":168,"passed_time":0.3451493424,"remaining_time":1.697154459},
{"learn":[0.4118146249],"iteration":169,"passed_time":0.3474118453,"remaining_time":1.696187245},
{"learn":[0.4111991156],"iteration":170,"passed_time":0.3495581657,"remaining_time":1.694641634},
{"learn":[0.4107251113],"iteration":171,"passed_time":0.3517308539,"remaining_time":1.693215971},
{"learn":[0.4104665474],"iteration":172,"passed_time":0.3537803312,"remaining_time":1.691192681},
{"learn":[0.4100454869],"iteration":173,"passed_time":0.3559132928,"remaining_time":1.689565401},
{"learn":[0.4096914703],"iteration":174,"passed_time":0.3576341712,"remaining_time":1.685989664},
{"learn":[0.4092307318],"iteration":175,"passed_time":0.3601805712,"remaining_time":1.686299947},
{"learn":[0.4091487604],"iteration":176,"passed_time":0.3618284551,"remaining_time":1.682400105},
{"learn":[0.4086560437],"iteration":177,"passed_time":0.364080474,"remaining_time":1.681315447},
{"learn":[0.4083522522],"iteration":178,"passed_time":0.3663499391,"remaining_time":1.680297765},
{"learn":[0.4080237314],"iteration":179,"passed_time":0.3684522358,"remaining_time":1.67850463},
{"learn":[0.4078175678],"iteration":180,"passed_time":0.3706066001,"remaining_time":1.676943677},
{"learn":[0.4073627776],"iteration":181,"passed_time":0.3725474319,"remaining_time":1.67441648},
{"learn":[0.4069850398],"iteration":182,"passed_time":0.3747897665,"remaining_time":1.673241744},
{"learn":[0.4069076398],"iteration":183,"passed_time":0.3760381691,"remaining_time":1.667647533},
{"learn":[0.4064493902],"iteration":184,"passed_time":0.3782917773,"remaining_time":1.666528641},
{"learn":[0.4059690344],"iteration":185,"passed_time":0.3805932659,"remaining_time":1.665607088},
{"learn":[0.4056146252],"iteration":186,"passed_time":0.3829077591,"remaining_time":1.664727316},
{"learn":[0.4051993047],"iteration":187,"passed_time":0.3853714518,"remaining_time":1.664476696},
{"learn":[0.4049742934],"iteration":188,"passed_time":0.3869847748,"remaining_time":1.660553716},
{"learn":[0.4046680494],"iteration":189,"passed_time":0.3891242295,"remaining_time":1.658898031},
{"learn":[0.4043852286],"iteration":190,"passed_time":0.3917339582,"remaining_time":1.659229174},
{"learn":[0.4038932396],"iteration":191,"passed_time":0.3939636681,"remaining_time":1.657930437},
{"learn":[0.4036137317],"iteration":192,"passed_time":0.396080245,"remaining_time":1.656149004},
{"learn":[0.4033887985],"iteration":193,"passed_time":0.3978128602,"remaining_time":1.652768894},
{"learn":[0.4030781217],"iteration":194,"passed_time":0.4000340657,"remaining_time":1.651422681},
{"learn":[0.4026665316],"iteration":195,"passed_time":0.4020855073,"remaining_time":1.649371163},
{"learn":[0.4025281816],"iteration":196,"passed_time":0.4034430883,"remaining_time":1.64449137},
{"learn":[0.4022146],"iteration":197,"passed_time":0.4056072476,"remaining_time":1.642914205},
{"learn":[0.4020704096],"iteration":198,"passed_time":0.4083347782,"remaining_time":1.643598781},
{"learn":[0.4018621366],"iteration":199,"passed_time":0.409916749,"remaining_time":1.639666996},
{"learn":[0.4015264839],"iteration":200,"passed_time":0.4122829809,"remaining_time":1.638876128},
{"learn":[0.4010108697],"iteration":201,"passed_time":0.4146107256,"remaining_time":1.637917619},
{"learn":[0.4006578693],"iteration":202,"passed_time":0.4170161538,"remaining_time":1.637250614},
{"learn":[0.4002507894],"iteration":203,"passed_time":0.4193975445,"remaining_time":1.636472772},
{"learn":[0.3997737064],"iteration":204,"passed_time":0.4220249912,"remaining_time":1.636633502},
{"learn":[0.39931885],"iteration":205,"passed_time":0.4251059662,"remaining_time":1.638515229},
{"learn":[0.3989492193],"iteration":206,"passed_time":0.4275923085,"remaining_time":1.638071018},
{"learn":[0.3988994778],"iteration":207,"passed_time":0.4287888576,"remaining_time":1.632696035},
{"learn":[0.3985059089],"iteration":208,"passed_time":0.431147336,"remaining_time":1.631758578},
{"learn":[0.3983472532],"iteration":209,"passed_time":0.4334462988,"remaining_time":1.630583695},
{"learn":[0.3979317735],"iteration":210,"passed_time":0.4357496351,"remaining_time":1.629414512},
{"learn":[0.3976381047],"iteration":211,"passed_time":0.4382914518,"remaining_time":1.629121057},
{"learn":[0.3974621193],"iteration":212,"passed_time":0.4411416353,"remaining_time":1.629945854},
{"learn":[0.3971502476],"iteration":213,"passed_time":0.443399622,"remaining_time":1.628561229},
{"learn":[0.396997032],"iteration":214,"passed_time":0.4455408213,"remaining_time":1.626742068},
{"learn":[0.3966829863],"iteration":215,"passed_time":0.4477543295,"remaining_time":1.625182381},
{"learn":[0.3964424607],"iteration":216,"passed_time":0.4499330694,"remaining_time":1.623491214},
{"learn":[0.3960351906],"iteration":217,"passed_time":0.4521629506,"remaining_time":1.621979025},
{"learn":[0.3957691663],"iteration":218,"passed_time":0.4549533978,"remaining_time":1.622459377},
{"learn":[0.3953212839],"iteration":219,"passed_time":0.4573725683,"remaining_time":1.621593651},
{"learn":[0.3950750752],"iteration":220,"passed_time":0.4596270198,"remaining_time":1.620133251},
{"learn":[0.3948059378],"iteration":221,"passed_time":0.4620437895,"remaining_time":1.619234542},
{"learn":[0.3943931626],"iteration":222,"passed_time":0.4645977316,"remaining_time":1.618800168},
{"learn":[0.3940369467],"iteration":223,"passed_time":0.4670946804,"remaining_time":1.618149429},
{"learn":[0.3936719059],"iteration":224,"passed_time":0.4699894423,"remaining_time":1.618852523},
{"learn":[0.3933767009],"iteration":225,"passed_time":0.4724054023,"remaining_time":1.617883988},
{"learn":[0.393049815],"iteration":226,"passed_time":0.474797814,"remaining_time":1.616822512},
{"learn":[0.3926471052],"iteration":227,"passed_time":0.4772252197,"remaining_time":1.615867849},
{"learn":[0.3923522137],"iteration":228,"passed_time":0.4796705146,"remaining_time":1.614960554},
{"learn":[0.3919780075],"iteration":229,"passed_time":0.481958839,"remaining_time":1.613514374},
{"learn":[0.3917592165],"iteration":230,"passed_time":0.4843634373,"remaining_time":1.61244798},
{"learn":[0.3913819773],"iteration":231,"passed_time":0.4874717661,"remaining_time":1.613699639},
{"learn":[0.3910579385],"iteration":232,"passed_time":0.4899138815,"remaining_time":1.612720803},
{"learn":[0.3908157819],"iteration":233,"passed_time":0.4922633578,"remaining_time":1.611426206},
{"learn":[0.3907737725],"iteration":234,"passed_time":0.4935881467,"remaining_time":1.606786946},
{"learn":[0.3905557194],"iteration":235,"passed_time":0.4958310938,"remaining_time":1.605148117},
{"learn":[0.390178422],"iteration":236,"passed_time":0.4982917959,"remaining_time":1.604205233},
{"learn":[0.3899322543],"iteration":237,"passed_time":0.500982974,"remaining_time":1.603987505},
{"learn":[0.3896820465],"iteration":238,"passed_time":0.504050299,"remaining_time":1.604946768},
{"learn":[0.3895350128],"iteration":239,"passed_time":0.5070006813,"remaining_time":1.605502158},
{"learn":[0.3894103942],"iteration":240,"passed_time":0.5096531196,"remaining_time":1.605090115},
{"learn":[0.3890661422],"iteration":241,"passed_time":0.5122065691,"remaining_time":1.604349502},
{"learn":[0.3887202359],"iteration":242,"passed_time":0.514863177,"remaining_time":1.603915329},
{"learn":[0.3884450165],"iteration":243,"passed_time":0.5185416571,"remaining_time":1.606629069},
{"learn":[0.3881620594],"iteration":244,"passed_time":0.5213379529,"remaining_time":1.606572059},
{"learn":[0.38812607],"iteration":245,"passed_time":0.5235100521,"remaining_time":1.604579591},
{"learn":[0.388034459],"iteration":246,"passed_time":0.5268764959,"remaining_time":1.606226726},
{"learn":[0.3877079191],"iteration":247,"passed_time":0.5297147454,"remaining_time":1.606231809},
{"learn":[0.3875087534],"iteration":248,"passed_time":0.5343200057,"remaining_time":1.611543471},
{"learn":[0.3872774875],"iteration":249,"passed_time":0.5371665877,"remaining_time":1.611499763},
{"learn":[0.3869640933],"iteration":250,"passed_time":0.5399803684,"remaining_time":1.61133584},
{"learn":[0.3867154315],"iteration":251,"passed_time":0.5428462292,"remaining_time":1.611305474},
{"learn":[0.3864517481],"iteration":252,"passed_time":0.5454150178,"remaining_time":1.610375567},
{"learn":[0.3861334819],"iteration":253,"passed_time":0.5491851696,"remaining_time":1.612961167},
{"learn":[0.3859932043],"iteration":254,"passed_time":0.551821339,"remaining_time":1.612183912},
{"learn":[0.385740444],"iteration":255,"passed_time":0.5541929455,"remaining_time":1.610623248},
{"learn":[0.385565837],"iteration":256,"passed_time":0.556764739,"remaining_time":1.609635024},
{"learn":[0.3854379387],"iteration":257,"passed_time":0.5589384224,"remaining_time":1.607489571},
{"learn":[0.3854165956],"iteration":258,"passed_time":0.5603563808,"remaining_time":1.603181769},
{"learn":[0.385056096],"iteration":259,"passed_time":0.5632811699,"remaining_time":1.603184868},
{"learn":[0.3847879614],"iteration":260,"passed_time":0.5660886814,"remaining_time":1.60283347},
{"learn":[0.384493857],"iteration":261,"passed_time":0.5691755446,"remaining_time":1.603250198},
{"learn":[0.3843072829],"iteration":262,"passed_time":0.5714447974,"remaining_time":1.601349109},
{"learn":[0.3841963683],"iteration":263,"passed_time":0.5743693582,"remaining_time":1.60127215},
{"learn":[0.3839779898],"iteration":264,"passed_time":0.5766215877,"remaining_time":1.599308932},
{"learn":[0.3837041917],"iteration":265,"passed_time":0.5792858879,"remaining_time":1.598480608},
{"learn":[0.3835403222],"iteration":266,"passed_time":0.5824220755,"remaining_time":1.598934013},
{"learn":[0.3832950573],"iteration":267,"passed_time":0.5852753545,"remaining_time":1.598587909},
{"learn":[0.3831554352],"iteration":268,"passed_time":0.5880223754,"remaining_time":1.597934411},
{"learn":[0.3829909123],"iteration":269,"passed_time":0.5906506923,"remaining_time":1.596944464},
{"learn":[0.3827807345],"iteration":270,"passed_time":0.5933257819,"remaining_time":1.596068247},
{"learn":[0.3826146577],"iteration":271,"passed_time":0.5977123693,"remaining_time":1.599759577},
{"learn":[0.3823480722],"iteration":272,"passed_time":0.6005341283,"remaining_time":1.599224583},
{"learn":[0.382082248],"iteration":273,"passed_time":0.6034618543,"remaining_time":1.598953672},
{"learn":[0.3817959786],"iteration":274,"passed_time":0.606875159,"remaining_time":1.599943601},
{"learn":[0.3816987293],"iteration":275,"passed_time":0.6091744935,"remaining_time":1.597979468},
{"learn":[0.3815237816],"iteration":276,"passed_time":0.6134667425,"remaining_time":1.601214638},
{"learn":[0.3813061732],"iteration":277,"passed_time":0.616244117,"remaining_time":1.60046134},
{"learn":[0.381145752],"iteration":278,"passed_time":0.6190939992,"remaining_time":1.599880908},
{"learn":[0.3809587089],"iteration":279,"passed_time":0.6219183335,"remaining_time":1.599218572},
{"learn":[0.3806921134],"iteration":280,"passed_time":0.6251273159,"remaining_time":1.599525054},
{"learn":[0.3805534223],"iteration":281,"passed_time":0.6280298028,"remaining_time":1.599026236},
{"learn":[0.3803540254],"iteration":282,"passed_time":0.6306014453,"remaining_time":1.597672213},
{"learn":[0.3801877758],"iteration":283,"passed_time":0.6359138597,"remaining_time":1.603219449},
{"learn":[0.3798142951],"iteration":284,"passed_time":0.6390098752,"remaining_time":1.603130038},
{"learn":[0.379487776],"iteration":285,"passed_time":0.6467009213,"remaining_time":1.614491111},
{"learn":[0.3791136305],"iteration":286,"passed_time":0.6498298329,"remaining_time":1.614385613},
{"learn":[0.3788127223],"iteration":287,"passed_time":0.6523943882,"remaining_time":1.612863904},
{"learn":[0.3786833827],"iteration":288,"passed_time":0.6545180582,"remaining_time":1.610250309},
{"learn":[0.3785008553],"iteration":289,"passed_time":0.6572089023,"remaining_time":1.609028692},
{"learn":[0.3783011637],"iteration":290,"passed_time":0.6605070499,"remaining_time":1.609276627},
{"learn":[0.378104465],"iteration":291,"passed_time":0.6628332472,"remaining_time":1.607143627},
{"learn":[0.3778961376],"iteration":292,"passed_time":0.6651572058,"remaining_time":1.605003906},
{"learn":[0.3777629575],"iteration":293,"passed_time":0.6672888282,"remaining_time":1.602401064},
{"learn":[0.3773652722],"iteration":294,"passed_time":0.6693444327,"remaining_time":1.599619746},
{"learn":[0.3771534903],"iteration":295,"passed_time":0.6713956361,"remaining_time":1.596832864},
{"learn":[0.3769273259],"iteration":296,"passed_time":0.6738580373,"remaining_time":1.595024243},
{"learn":[0.3766925482],"iteration":297,"passed_time":0.6763035857,"remaining_time":1.593171534},
{"learn":[0.3764561396],"iteration":298,"passed_time":0.6785205099,"remaining_time":1.590778854},
{"learn":[0.3762689975],"iteration":299,"passed_time":0.6806169437,"remaining_time":1.588106202},
{"learn":[0.3759932732],"iteration":300,"passed_time":0.6827810653,"remaining_time":1.585594567},
{"learn":[0.3757339281],"iteration":301,"passed_time":0.6849569917,"remaining_time":1.583112517},
{"learn":[0.3756334481],"iteration":302,"passed_time":0.6869323391,"remaining_time":1.58017109},
{"learn":[0.3753708841],"iteration":303,"passed_time":0.689804417,"remaining_time":1.57928906},
{"learn":[0.3751716883],"iteration":304,"passed_time":0.6923013163,"remaining_time":1.577539065},
{"learn":[0.3749045408],"iteration":305,"passed_time":0.6946579361,"remaining_time":1.575466038},
{"learn":[0.3746986614],"iteration":306,"passed_time":0.6969272023,"remaining_time":1.573193978},
{"learn":[0.3746543997],"iteration":307,"passed_time":0.6986424988,"remaining_time":1.569677303},
{"learn":[0.3743754654],"iteration":308,"passed_time":0.7008044547,"remaining_time":1.567171127},
{"learn":[0.3741400582],"iteration":309,"passed_time":0.7030436341,"remaining_time":1.564839057},
{"learn":[0.3739116211],"iteration":310,"passed_time":0.7059644122,"remaining_time":1.564017621},
{"learn":[0.3738309743],"iteration":311,"passed_time":0.7082255742,"remaining_time":1.561728189},
{"learn":[0.3737025413],"iteration":312,"passed_time":0.7107027314,"remaining_time":1.559913024},
{"learn":[0.3736661257],"iteration":313,"passed_time":0.7125327797,"remaining_time":1.556679895},
{"learn":[0.3734826234],"iteration":314,"passed_time":0.7146771526,"remaining_time":1.554139205},
{"learn":[0.3733034945],"iteration":315,"passed_time":0.7168768765,"remaining_time":1.551720834},
{"learn":[0.3732181909],"iteration":316,"passed_time":0.7186217681,"remaining_time":1.548323872},
{"learn":[0.3730756687],"iteration":317,"passed_time":0.7210181354,"remaining_time":1.546334492},
{"learn":[0.3729311146],"iteration":318,"passed_time":0.7237072266,"remaining_time":1.544967465},
{"learn":[0.372913357],"iteration":319,"passed_time":0.7251168667,"remaining_time":1.540873342},
{"learn":[0.3726992073],"iteration":320,"passed_time":0.727182127,"remaining_time":1.538182755},
{"learn":[0.3725904492],"iteration":321,"passed_time":0.7292799512,"remaining_time":1.535564618},
{"learn":[0.3725273839],"iteration":322,"passed_time":0.731352642,"remaining_time":1.532897024},
{"learn":[0.3723617929],"iteration":323,"passed_time":0.7335814826,"remaining_time":1.530558896},
{"learn":[0.3721091898],"iteration":324,"passed_time":0.7357728035,"remaining_time":1.528143515},
{"learn":[0.3719504166],"iteration":325,"passed_time":0.7387665828,"remaining_time":1.527388579},
{"learn":[0.3717233352],"iteration":326,"passed_time":0.7412615144,"remaining_time":1.52559327},
{"learn":[0.3715543373],"iteration":327,"passed_time":0.7435882529,"remaining_time":1.523449104},
{"learn":[0.3712023791],"iteration":328,"passed_time":0.7458572112,"remaining_time":1.521185984},
{"learn":[0.3710887394],"iteration":329,"passed_time":0.748011922,"remaining_time":1.518690872},
{"learn":[0.3709325622],"iteration":330,"passed_time":0.7500660841,"remaining_time":1.515994593},
{"learn":[0.3707088037],"iteration":331,"passed_time":0.7523933967,"remaining_time":1.513851774},
{"learn":[0.3706715599],"iteration":332,"passed_time":0.7542900252,"remaining_time":1.510845186},
{"learn":[0.3705772104],"iteration":333,"passed_time":0.7562012049,"remaining_time":1.507874259},
{"learn":[0.3703894313],"iteration":334,"passed_time":0.7584550388,"remaining_time":1.505589853},
{"learn":[0.3701557658],"iteration":335,"passed_time":0.7607573799,"remaining_time":1.503401489},
{"learn":[0.3699833228],"iteration":336,"passed_time":0.7629395116,"remaining_time":1.500975953},
{"learn":[0.3698102462],"iteration":337,"passed_time":0.765018474,"remaining_time":1.498349792},
{"learn":[0.3697490794],"iteration":338,"passed_time":0.7665466998,"remaining_time":1.494653005},
{"learn":[0.3695665169],"iteration":339,"passed_time":0.7691243286,"remaining_time":1.49300605},
{"learn":[0.3695259506],"iteration":340,"passed_time":0.771765187,"remaining_time":1.491475831},
{"learn":[0.3693554053],"iteration":341,"passed_time":0.7741017165,"remaining_time":1.489353595},
{"learn":[0.3692910082],"iteration":342,"passed_time":0.7764890255,"remaining_time":1.487327375},
{"learn":[0.3691740702],"iteration":343,"passed_time":0.7786062141,"remaining_time":1.484783943},
{"learn":[0.3689734536],"iteration":344,"passed_time":0.7807166293,"remaining_time":1.482230122},
{"learn":[0.3688740837],"iteration":345,"passed_time":0.7828604106,"remaining_time":1.479741932},
{"learn":[0.3686360395],"iteration":346,"passed_time":0.785721277,"remaining_time":1.47860517},
{"learn":[0.368390354],"iteration":347,"passed_time":0.7880275099,"remaining_time":1.476419358},
{"learn":[0.3681454007],"iteration":348,"passed_time":0.7902182695,"remaining_time":1.47401746},
{"learn":[0.3679753883],"iteration":349,"passed_time":0.7922701047,"remaining_time":1.471358766},
{"learn":[0.3677620706],"iteration":350,"passed_time":0.7946369475,"remaining_time":1.46928598},
{"learn":[0.367592909],"iteration":351,"passed_time":0.7968655708,"remaining_time":1.466957073},
{"learn":[0.3673410313],"iteration":352,"passed_time":0.7990847422,"remaining_time":1.464611411},
{"learn":[0.3672506453],"iteration":353,"passed_time":0.8018824855,"remaining_time":1.463322276},
{"learn":[0.3670127152],"iteration":354,"passed_time":0.8040121108,"remaining_time":1.460810737},
{"learn":[0.3668201239],"iteration":355,"passed_time":0.8061705574,"remaining_time":1.45835348},
{"learn":[0.3667536105],"iteration":356,"passed_time":0.8084641305,"remaining_time":1.456141277},
{"learn":[0.366626696],"iteration":357,"passed_time":0.81072469,"remaining_time":1.453869416},
{"learn":[0.3664654191],"iteration":358,"passed_time":0.8129136387,"remaining_time":1.451469756},
{"learn":[0.3662202653],"iteration":359,"passed_time":0.814985461,"remaining_time":1.448863042},
{"learn":[0.3660828015],"iteration":360,"passed_time":0.8179556374,"remaining_time":1.447849452},
{"learn":[0.3658682367],"iteration":361,"passed_time":0.8202276719,"remaining_time":1.445594626},
{"learn":[0.3658240079],"iteration":362,"passed_time":0.82200177,"remaining_time":1.442465916},
{"learn":[0.3657384489],"iteration":363,"passed_time":0.8241539064,"remaining_time":1.440005177},
{"learn":[0.365712211],"iteration":364,"passed_time":0.8255361919,"remaining_time":1.4362068},
{"learn":[0.3655879117],"iteration":365,"passed_time":0.8277627317,"remaining_time":1.433884076},
{"learn":[0.365535578],"iteration":366,"passed_time":0.8291889235,"remaining_time":1.43018144},
{"learn":[0.3654861672],"iteration":367,"passed_time":0.8305304705,"remaining_time":1.426345808},
{"learn":[0.3653310584],"iteration":368,"passed_time":0.8330309739,"remaining_time":1.424505541},
{"learn":[0.36516721],"iteration":369,"passed_time":0.8351726607,"remaining_time":1.422050747},
{"learn":[0.3648473571],"iteration":370,"passed_time":0.837234838,"remaining_time":1.419462839},
{"learn":[0.364706588],"iteration":371,"passed_time":0.8391613393,"remaining_time":1.416648713},
{"learn":[0.3646693401],"iteration":372,"passed_time":0.8405916085,"remaining_time":1.413005197},
{"learn":[0.3646175128],"iteration":373,"passed_time":0.8426323395,"remaining_time":1.410395306},
{"learn":[0.3643559843],"iteration":374,"passed_time":0.8446824008,"remaining_time":1.407804001},
{"learn":[0.3641738728],"iteration":375,"passed_time":0.8468014078,"remaining_time":1.405329996},
{"learn":[0.3640122884],"iteration":376,"passed_time":0.8492715442,"remaining_time":1.403438122},
{"learn":[0.3639899368],"iteration":377,"passed_time":0.8511091999,"remaining_time":1.40050244},
{"learn":[0.3639265992],"iteration":378,"passed_time":0.853243416,"remaining_time":1.398058473},
{"learn":[0.3635841288],"iteration":379,"passed_time":0.8553477174,"remaining_time":1.395567328},
{"learn":[0.3634395549],"iteration":380,"passed_time":0.8576376588,"remaining_time":1.393379818},
{"learn":[0.3632155114],"iteration":381,"passed_time":0.8598691368,"remaining_time":1.39109719},
{"learn":[0.3630563136],"iteration":382,"passed_time":0.8620845472,"remaining_time":1.388788944},
{"learn":[0.363000932],"iteration":383,"passed_time":0.8641208511,"remaining_time":1.386193865},
{"learn":[0.3627905962],"iteration":384,"passed_time":0.8665425079,"remaining_time":1.384217253},
{"learn":[0.3627525723],"iteration":385,"passed_time":0.8682565575,"remaining_time":1.381112763},
{"learn":[0.3625484091],"iteration":386,"passed_time":0.8706647313,"remaining_time":1.379114936},
{"learn":[0.3623787276],"iteration":387,"passed_time":0.872930073,"remaining_time":1.376889703},
{"learn":[0.362292954],"iteration":388,"passed_time":0.8751384415,"remaining_time":1.374574776},
{"learn":[0.3620724597],"iteration":389,"passed_time":0.8772695671,"remaining_time":1.372139579},
{"learn":[0.3620111485],"iteration":390,"passed_time":0.8796282285,"remaining_time":1.370060335},
{"learn":[0.3617651245],"iteration":391,"passed_time":0.8820567955,"remaining_time":1.368088091},
{"learn":[0.3616002042],"iteration":392,"passed_time":0.8841012078,"remaining_time":1.365520186},
{"learn":[0.3613744584],"iteration":393,"passed_time":0.8860860684,"remaining_time":1.362863344},
{"learn":[0.3612431487],"iteration":394,"passed_time":0.8881941844,"remaining_time":1.360398688},
{"learn":[0.3610740569],"iteration":395,"passed_time":0.890440624,"remaining_time":1.35814681},
{"learn":[0.3608757441],"iteration":396,"passed_time":0.8926379505,"remaining_time":1.355820363},
{"learn":[0.3607669793],"iteration":397,"passed_time":0.8948872129,"remaining_time":1.353573121},
{"learn":[0.3606126755],"iteration":398,"passed_time":0.8979889344,"remaining_time":1.352609899},
{"learn":[0.3604593307],"iteration":399,"passed_time":0.9001906193,"remaining_time":1.350285929},
{"learn":[0.3603137568],"iteration":400,"passed_time":0.9024924738,"remaining_time":1.348112199},
{"learn":[0.3602553331],"iteration":401,"passed_time":0.904718463,"remaining_time":1.345824977},
{"learn":[0.3600855585],"iteration":402,"passed_time":0.9068763818,"remaining_time":1.343437221},
{"learn":[0.3600789677],"iteration":403,"passed_time":0.9081097097,"remaining_time":1.339686601},
{"learn":[0.3599918994],"iteration":404,"passed_time":0.9102346308,"remaining_time":1.337258285},
{"learn":[0.3598635178],"iteration":405,"passed_time":0.913055711,"remaining_time":1.335849981},
{"learn":[0.3596395854],"iteration":406,"passed_time":0.9156435998,"remaining_time":1.334094975},
{"learn":[0.3595195219],"iteration":407,"passed_time":0.9178107497,"remaining_time":1.331725402},
{"learn":[0.3592843055],"iteration":408,"passed_time":0.9200156267,"remaining_time":1.329411333},
{"learn":[0.3590706675],"iteration":409,"passed_time":0.9221753891,"remaining_time":1.327032877},
{"learn":[0.358919756],"iteration":410,"passed_time":0.9243207747,"remaining_time":1.324634882},
{"learn":[0.3587754222],"iteration":411,"passed_time":0.9265561832,"remaining_time":1.322366592},
{"learn":[0.3586241402],"iteration":412,"passed_time":0.929394509,"remaining_time":1.320955392},
{"learn":[0.358503448],"iteration":413,"passed_time":0.9315777509,"remaining_time":1.318610053},
{"learn":[0.358386004],"iteration":414,"passed_time":0.9340772045,"remaining_time":1.31671124},
{"learn":[0.3582261915],"iteration":415,"passed_time":0.9363151672,"remaining_time":1.314442446},
{"learn":[0.3581531995],"iteration":416,"passed_time":0.93825529,"remaining_time":1.311757396},
{"learn":[0.357941754],"iteration":417,"passed_time":0.9404863887,"remaining_time":1.309481048},
{"learn":[0.3577655889],"iteration":418,"passed_time":0.943400609,"remaining_time":1.308152157},
{"learn":[0.3576822764],"iteration":419,"passed_time":0.9458423805,"remaining_time":1.306163287},
{"learn":[0.3575499936],"iteration":420,"passed_time":0.9482203106,"remaining_time":1.304084465},
{"learn":[0.3574231237],"iteration":421,"passed_time":0.950535038,"remaining_time":1.301917659},
{"learn":[0.3573810765],"iteration":422,"passed_time":0.9520654321,"remaining_time":1.29868027},
{"learn":[0.3572795133],"iteration":423,"passed_time":0.9543921388,"remaining_time":1.296532717},
{"learn":[0.3571832871],"iteration":424,"passed_time":0.9565612314,"remaining_time":1.294171078},
{"learn":[0.3570473699],"iteration":425,"passed_time":0.9588648387,"remaining_time":1.29199159},
{"learn":[0.3569472327],"iteration":426,"passed_time":0.9615747309,"remaining_time":1.290356723},
{"learn":[0.35686448],"iteration":427,"passed_time":0.9638712552,"remaining_time":1.288164388},
{"learn":[0.3567757264],"iteration":428,"passed_time":0.9664806633,"remaining_time":1.286388016},
{"learn":[0.3566469668],"iteration":429,"passed_time":0.968878317,"remaining_time":1.284327071},
{"learn":[0.356352005],"iteration":430,"passed_time":0.9713061481,"remaining_time":1.282304404},
{"learn":[0.3561079889],"iteration":431,"passed_time":0.9736748663,"remaining_time":1.280202139},
{"learn":[0.3559869361],"iteration":432,"passed_time":0.9763897152,"remaining_time":1.27855189},
{"learn":[0.3559497267],"iteration":433,"passed_time":0.9785335938,"remaining_time":1.276152106},
{"learn":[0.3558115893],"iteration":434,"passed_time":0.9807489506,"remaining_time":1.273846338},
{"learn":[0.3556471725],"iteration":435,"passed_time":0.9829186431,"remaining_time":1.271481914},
{"learn":[0.355473768],"iteration":436,"passed_time":0.9850782687,"remaining_time":1.269105413},
{"learn":[0.3551428916],"iteration":437,"passed_time":0.987312838,"remaining_time":1.266826062},
{"learn":[0.3551218895],"iteration":438,"passed_time":0.988948454,"remaining_time":1.26378151},
{"learn":[0.3550884369],"iteration":439,"passed_time":0.9910119177,"remaining_time":1.261287895},
{"learn":[0.354955329],"iteration":440,"passed_time":0.9931572799,"remaining_time":1.258900044},
{"learn":[0.354939001],"iteration":441,"passed_time":0.9943709387,"remaining_time":1.255337067},
{"learn":[0.3547080708],"iteration":442,"passed_time":0.9963566795,"remaining_time":1.252755464},
{"learn":[0.3544220436],"iteration":443,"passed_time":0.9984914201,"remaining_time":1.25036313},
{"learn":[0.3543392343],"iteration":444,"passed_time":1.000571164,"remaining_time":1.247903362},
{"learn":[0.3541457151],"iteration":445,"passed_time":1.002666666,"remaining_time":1.245464872},
{"learn":[0.3540338427],"iteration":446,"passed_time":1.004641611,"remaining_time":1.242878771},
{"learn":[0.3538918457],"iteration":447,"passed_time":1.00741133,"remaining_time":1.241274674},
{"learn":[0.3537467119],"iteration":448,"passed_time":1.009584614,"remaining_time":1.238933457},
{"learn":[0.3535717038],"iteration":449,"passed_time":1.011718861,"remaining_time":1.236545274},
{"learn":[0.3534872465],"iteration":450,"passed_time":1.013727615,"remaining_time":1.234005456},
{"learn":[0.3534066863],"iteration":451,"passed_time":1.015356998,"remaining_time":1.231008041},
{"learn":[0.3533347968],"iteration":452,"passed_time":1.017429796,"remaining_time":1.228552093},
{"learn":[0.353280236],"iteration":453,"passed_time":1.019479524,"remaining_time":1.226070088},
{"learn":[0.3532136654],"iteration":454,"passed_time":1.022090178,"remaining_time":1.224261862},
{"learn":[0.3529395384],"iteration":455,"passed_time":1.024499397,"remaining_time":1.222209807},
{"learn":[0.3526734115],"iteration":456,"passed_time":1.026658955,"remaining_time":1.219859546},
{"learn":[0.3525395822],"iteration":457,"passed_time":1.028792146,"remaining_time":1.217478915},
{"learn":[0.3524154232],"iteration":458,"passed_time":1.030799959,"remaining_time":1.214951586},
{"learn":[0.3522446831],"iteration":459,"passed_time":1.032812912,"remaining_time":1.212432549},
{"learn":[0.3520351629],"iteration":460,"passed_time":1.034968124,"remaining_time":1.210082036},
{"learn":[0.3519188371],"iteration":461,"passed_time":1.037145944,"remaining_time":1.207758696},
{"learn":[0.351802424],"iteration":462,"passed_time":1.039373263,"remaining_time":1.205493396},
{"learn":[0.3517536806],"iteration":463,"passed_time":1.040989557,"remaining_time":1.20252242},
{"learn":[0.3516614771],"iteration":464,"passed_time":1.042988993,"remaining_time":1.199998088},
{"learn":[0.3515404332],"iteration":465,"passed_time":1.045020159,"remaining_time":1.197512371},
{"learn":[0.3515015081],"iteration":466,"passed_time":1.046995449,"remaining_time":1.194964827},
{"learn":[0.351405797],"iteration":467,"passed_time":1.049030308,"remaining_time":1.192487444},
{"learn":[0.3511740074],"iteration":468,"passed_time":1.051202537,"remaining_time":1.190167478},
{"learn":[0.3511316611],"iteration":469,"passed_time":1.053794856,"remaining_time":1.188321858},
{"learn":[0.3510510227],"iteration":470,"passed_time":1.056227776,"remaining_time":1.186294041},
{"learn":[0.3509062829],"iteration":471,"passed_time":1.058402154,"remaining_time":1.183975291},
{"learn":[0.3508755449],"iteration":472,"passed_time":1.060503945,"remaining_time":1.181576277},
{"learn":[0.3507392583],"iteration":473,"passed_time":1.0626118,"remaining_time":1.179185246},
{"learn":[0.3505745279],"iteration":474,"passed_time":1.064645066,"remaining_time":1.176712968},
{"learn":[0.3504011329],"iteration":475,"passed_time":1.066853299,"remaining_time":1.174435144},
{"learn":[0.350354939],"iteration":476,"passed_time":1.069300555,"remaining_time":1.172419686},
{"learn":[0.3502063292],"iteration":477,"passed_time":1.071619755,"remaining_time":1.170262577},
{"learn":[0.3500065112],"iteration":478,"passed_time":1.073611984,"remaining_time":1.167749151},
{"learn":[0.3497848807],"iteration":479,"passed_time":1.075645848,"remaining_time":1.165283002},
{"learn":[0.349617312],"iteration":480,"passed_time":1.077693867,"remaining_time":1.162833923},
{"learn":[0.3495077301],"iteration":481,"passed_time":1.080096864,"remaining_time":1.160767999},
{"learn":[0.3493538488],"iteration":482,"passed_time":1.082283868,"remaining_time":1.158469482},
{"learn":[0.3492320129],"iteration":483,"passed_time":1.084414883,"remaining_time":1.156111735},
{"learn":[0.3491186857],"iteration":484,"passed_time":1.087218402,"remaining_time":1.154469025},
{"learn":[0.3491001808],"iteration":485,"passed_time":1.089216935,"remaining_time":1.151970174},
{"learn":[0.3489383524],"iteration":486,"passed_time":1.091351781,"remaining_time":1.149616968},
{"learn":[0.3487421084],"iteration":487,"passed_time":1.093474343,"remaining_time":1.14725177},
{"learn":[0.3485989179],"iteration":488,"passed_time":1.095986357,"remaining_time":1.145294537},
{"learn":[0.3484717982],"iteration":489,"passed_time":1.09830565,"remaining_time":1.143134452},
{"learn":[0.3482890745],"iteration":490,"passed_time":1.100722419,"remaining_time":1.141074769},
{"learn":[0.3481423858],"iteration":491,"passed_time":1.103381644,"remaining_time":1.139263974},
{"learn":[0.3479369913],"iteration":492,"passed_time":1.105404171,"remaining_time":1.136794959},
{"learn":[0.3479047535],"iteration":493,"passed_time":1.107359261,"remaining_time":1.134258676},
{"learn":[0.3477365182],"iteration":494,"passed_time":1.109238741,"remaining_time":1.131647605},
{"learn":[0.3475158627],"iteration":495,"passed_time":1.11117097,"remaining_time":1.129093083},
{"learn":[0.3473037533],"iteration":496,"passed_time":1.113079868,"remaining_time":1.126517452},
{"learn":[0.3472060455],"iteration":497,"passed_time":1.11500871,"remaining_time":1.123964603},
{"learn":[0.3471403455],"iteration":498,"passed_time":1.117160096,"remaining_time":1.121637692},
{"learn":[0.3469372926],"iteration":499,"passed_time":1.119523929,"remaining_time":1.119523929},
{"learn":[0.346822324],"iteration":500,"passed_time":1.121610276,"remaining_time":1.11713279},
{"learn":[0.3466973651],"iteration":501,"passed_time":1.123691954,"remaining_time":1.114738233},
{"learn":[0.346543348],"iteration":502,"passed_time":1.125651595,"remaining_time":1.112224339},
{"learn":[0.3464755189],"iteration":503,"passed_time":1.127546976,"remaining_time":1.109649405},
{"learn":[0.3463660286],"iteration":504,"passed_time":1.129558296,"remaining_time":1.107190805},
{"learn":[0.3462130847],"iteration":505,"passed_time":1.131749151,"remaining_time":1.10490925},
{"learn":[0.3461139062],"iteration":506,"passed_time":1.133976051,"remaining_time":1.102663103},
{"learn":[0.346068033],"iteration":507,"passed_time":1.136046858,"remaining_time":1.100265854},
{"learn":[0.3459837016],"iteration":508,"passed_time":1.138166775,"remaining_time":1.097917262},
{"learn":[0.3459756693],"iteration":509,"passed_time":1.139568777,"remaining_time":1.094879806},
{"learn":[0.3457248325],"iteration":510,"passed_time":1.141641893,"remaining_time":1.09249097},
{"learn":[0.345610017],"iteration":511,"passed_time":1.143680153,"remaining_time":1.090070146},
{"learn":[0.3454164983],"iteration":512,"passed_time":1.145790831,"remaining_time":1.08771956},
{"learn":[0.3452686405],"iteration":513,"passed_time":1.148204112,"remaining_time":1.085656028},
{"learn":[0.3451636003],"iteration":514,"passed_time":1.150582813,"remaining_time":1.083558572},
{"learn":[0.3450991718],"iteration":515,"passed_time":1.152633398,"remaining_time":1.081152257},
{"learn":[0.345086392],"iteration":516,"passed_time":1.154005625,"remaining_time":1.078113573},
{"learn":[0.3450392026],"iteration":517,"passed_time":1.156135114,"remaining_time":1.075785955},
{"learn":[0.3450087417],"iteration":518,"passed_time":1.158283,"remaining_time":1.073476152},
{"learn":[0.3449410407],"iteration":519,"passed_time":1.160519806,"remaining_time":1.071249051},
{"learn":[0.3447912161],"iteration":520,"passed_time":1.162722105,"remaining_time":1.068990188},
{"learn":[0.3446889554],"iteration":521,"passed_time":1.165547437,"remaining_time":1.067302059},
{"learn":[0.3446262387],"iteration":522,"passed_time":1.167861192,"remaining_time":1.065142999},
{"learn":[0.3444984467],"iteration":523,"passed_time":1.170120325,"remaining_time":1.06293373},
{"learn":[0.3444191511],"iteration":524,"passed_time":1.17184828,"remaining_time":1.060243682},
{"learn":[0.3442897204],"iteration":525,"passed_time":1.174093934,"remaining_time":1.058023812},
{"learn":[0.3442739516],"iteration":526,"passed_time":1.175486403,"remaining_time":1.055038081},
{"learn":[0.3441641941],"iteration":527,"passed_time":1.177657848,"remaining_time":1.052754743},
{"learn":[0.343969495],"iteration":528,"passed_time":1.180137582,"remaining_time":1.050746316},
{"learn":[0.343816137],"iteration":529,"passed_time":1.182936439,"remaining_time":1.049019106},
{"learn":[0.3436022868],"iteration":530,"passed_time":1.185256325,"remaining_time":1.046864815},
{"learn":[0.3435820219],"iteration":531,"passed_time":1.186799209,"remaining_time":1.044026372},
{"learn":[0.3435786494],"iteration":532,"passed_time":1.18798702,"remaining_time":1.040881685},
{"learn":[0.3435267988],"iteration":533,"passed_time":1.190035049,"remaining_time":1.038495006},
{"learn":[0.34344411],"iteration":534,"passed_time":1.192015565,"remaining_time":1.036050912},
{"learn":[0.3433456394],"iteration":535,"passed_time":1.194077431,"remaining_time":1.03367897},
{"learn":[0.3431235494],"iteration":536,"passed_time":1.196904233,"remaining_time":1.031967709},
{"learn":[0.3430732473],"iteration":537,"passed_time":1.199253798,"remaining_time":1.029842481},
{"learn":[0.3430213709],"iteration":538,"passed_time":1.201434598,"remaining_time":1.027572077},
{"learn":[0.3428393005],"iteration":539,"passed_time":1.20374644,"remaining_time":1.025413634},
{"learn":[0.342704143],"iteration":540,"passed_time":1.205982471,"remaining_time":1.023190304},
{"learn":[0.3425472749],"iteration":541,"passed_time":1.208409443,"remaining_time":1.021128275},
{"learn":[0.3424259446],"iteration":542,"passed_time":1.210956577,"remaining_time":1.019166033},
{"learn":[0.3422500437],"iteration":543,"passed_time":1.270583646,"remaining_time":1.065048056},
{"learn":[0.34216975],"iteration":544,"passed_time":1.273217456,"remaining_time":1.062961363},
{"learn":[0.3420303171],"iteration":545,"passed_time":1.278179727,"remaining_time":1.062808784},
{"learn":[0.3419621988],"iteration":546,"passed_time":1.280997311,"remaining_time":1.06086249},
{"learn":[0.3418148428],"iteration":547,"passed_time":1.283881098,"remaining_time":1.058967621},
{"learn":[0.3416987427],"iteration":548,"passed_time":1.286652571,"remaining_time":1.056976884},
{"learn":[0.3416239942],"iteration":549,"passed_time":1.297905146,"remaining_time":1.061922392},
{"learn":[0.341493486],"iteration":550,"passed_time":1.300940063,"remaining_time":1.060112683},
{"learn":[0.3414037592],"iteration":551,"passed_time":1.30389303,"remaining_time":1.058232024},
{"learn":[0.3412869557],"iteration":552,"passed_time":1.306833317,"remaining_time":1.056337238},
{"learn":[0.3411181683],"iteration":553,"passed_time":1.310103617,"remaining_time":1.054704356},
{"learn":[0.3410146182],"iteration":554,"passed_time":1.312642162,"remaining_time":1.05247885},
{"learn":[0.340889224],"iteration":555,"passed_time":1.315448476,"remaining_time":1.050466049},
{"learn":[0.3408127452],"iteration":556,"passed_time":1.318266778,"remaining_time":1.048459933},
{"learn":[0.3406779924],"iteration":557,"passed_time":1.320859847,"remaining_time":1.046272495},
{"learn":[0.3405563259],"iteration":558,"passed_time":1.323500914,"remaining_time":1.044121473},
{"learn":[0.3404528409],"iteration":559,"passed_time":1.326900896,"remaining_time":1.042564989},
{"learn":[0.3404016023],"iteration":560,"passed_time":1.329594232,"remaining_time":1.040448962},
{"learn":[0.3401718888],"iteration":561,"passed_time":1.332283071,"remaining_time":1.038327376},
{"learn":[0.3400242778],"iteration":562,"passed_time":1.334950239,"remaining_time":1.036186953},
{"learn":[0.3399240825],"iteration":563,"passed_time":1.337533386,"remaining_time":1.033979709},
{"learn":[0.3398358049],"iteration":564,"passed_time":1.341712966,"remaining_time":1.033000248},
{"learn":[0.3398354015],"iteration":565,"passed_time":1.343293533,"remaining_time":1.030016596},
{"learn":[0.3397849808],"iteration":566,"passed_time":1.345704521,"remaining_time":1.027672059},
{"learn":[0.3397738122],"iteration":567,"passed_time":1.347553368,"remaining_time":1.024899745},
{"learn":[0.3397384586],"iteration":568,"passed_time":1.349388863,"remaining_time":1.022120562},
{"learn":[0.3396394852],"iteration":569,"passed_time":1.352351185,"remaining_time":1.020194754},
{"learn":[0.3395574599],"iteration":570,"passed_time":1.354906489,"remaining_time":1.017959516},
{"learn":[0.339506705],"iteration":571,"passed_time":1.358139574,"remaining_time":1.016230311},
{"learn":[0.339418679],"iteration":572,"passed_time":1.360719733,"remaining_time":1.014009295},
{"learn":[0.3392406326],"iteration":573,"passed_time":1.36325767,"remaining_time":1.011755692},
{"learn":[0.3391289126],"iteration":574,"passed_time":1.365731108,"remaining_time":1.009453428},
{"learn":[0.3390290555],"iteration":575,"passed_time":1.367978459,"remaining_time":1.006984143},
{"learn":[0.3389068048],"iteration":576,"passed_time":1.370206046,"remaining_time":1.004501139},
{"learn":[0.3388158119],"iteration":577,"passed_time":1.372955617,"remaining_time":1.002400122},
{"learn":[0.3386780368],"iteration":578,"passed_time":1.375197815,"remaining_time":0.9999279447},
{"learn":[0.3385577685],"iteration":579,"passed_time":1.377250927,"remaining_time":0.9973196368},
{"learn":[0.3384103615],"iteration":580,"passed_time":1.379312527,"remaining_time":0.9947193612},
{"learn":[0.3382106743],"iteration":581,"passed_time":1.381514048,"remaining_time":0.9922214294},
{"learn":[0.3381078671],"iteration":582,"passed_time":1.383739295,"remaining_time":0.9897414855},
{"learn":[0.3378864628],"iteration":583,"passed_time":1.385904836,"remaining_time":0.9872198829},
{"learn":[0.3378117708],"iteration":584,"passed_time":1.38853088,"remaining_time":0.98502618},
{"learn":[0.337789781],"iteration":585,"passed_time":1.390808502,"remaining_time":0.9825848458},
{"learn":[0.3377664442],"iteration":586,"passed_time":1.392331881,"remaining_time":0.9796134015},
{"learn":[0.3375774311],"iteration":587,"passed_time":1.394383109,"remaining_time":0.9770167363},
{"learn":[0.3374230568],"iteration":588,"passed_time":1.396353965,"remaining_time":0.9743658396},
{"learn":[0.3374054693],"iteration":589,"passed_time":1.39809752,"remaining_time":0.9715592933},
{"learn":[0.3372413888],"iteration":590,"passed_time":1.400087493,"remaining_time":0.9689268776},
{"learn":[0.3371026384],"iteration":591,"passed_time":1.40225102,"remaining_time":0.9664162439},
{"learn":[0.3370055565],"iteration":592,"passed_time":1.404914301,"remaining_time":0.9642497817},
{"learn":[0.3368869878],"iteration":593,"passed_time":1.406997437,"remaining_time":0.961685117},
{"learn":[0.3368339136],"iteration":594,"passed_time":1.409079026,"remaining_time":0.9591210178},
{"learn":[0.3367298404],"iteration":595,"passed_time":1.411041181,"remaining_time":0.956477579},
{"learn":[0.3366325684],"iteration":596,"passed_time":1.412888878,"remaining_time":0.9537591586},
{"learn":[0.3366133367],"iteration":597,"passed_time":1.414294986,"remaining_time":0.9507467965},
{"learn":[0.3364294106],"iteration":598,"passed_time":1.416158851,"remaining_time":0.9480462423},
{"learn":[0.3363009815],"iteration":599,"passed_time":1.41823383,"remaining_time":0.9454892199},
{"learn":[0.3361614166],"iteration":600,"passed_time":1.421077107,"remaining_time":0.9434438699},
{"learn":[0.3360148354],"iteration":601,"passed_time":1.423370399,"remaining_time":0.9410322574},
{"learn":[0.3358526575],"iteration":602,"passed_time":1.425358271,"remaining_time":0.938419956},
{"learn":[0.3357092023],"iteration":603,"passed_time":1.427302472,"remaining_time":0.9357810912},
{"learn":[0.3355760968],"iteration":604,"passed_time":1.429268726,"remaining_time":0.93315892},
{"learn":[0.335447727],"iteration":605,"passed_time":1.431240921,"remaining_time":0.9305427772},
{"learn":[0.3353763413],"iteration":606,"passed_time":1.433293118,"remaining_time":0.9279805526},
{"learn":[0.3351610554],"iteration":607,"passed_time":1.435610587,"remaining_time":0.9255910363},
{"learn":[0.3350140303],"iteration":608,"passed_time":1.438229056,"remaining_time":0.9233950096},
{"learn":[0.3348085444],"iteration":609,"passed_time":1.440630576,"remaining_time":0.921058893},
{"learn":[0.3347002259],"iteration":610,"passed_time":1.442738568,"remaining_time":0.9185356841},
{"learn":[0.3345874733],"iteration":611,"passed_time":1.444916625,"remaining_time":0.9160582524},
{"learn":[0.3345654523],"iteration":612,"passed_time":1.446448361,"remaining_time":0.9131737612},
{"learn":[0.3344674446],"iteration":613,"passed_time":1.448463472,"remaining_time":0.9105975572},
{"learn":[0.3343055093],"iteration":614,"passed_time":1.450703567,"remaining_time":0.9081640215},
{"learn":[0.3341515453],"iteration":615,"passed_time":1.453331203,"remaining_time":0.905972698},
{"learn":[0.3340639106],"iteration":616,"passed_time":1.455478252,"remaining_time":0.9034816377},
{"learn":[0.3339966595],"iteration":617,"passed_time":1.457668608,"remaining_time":0.9010184599},
{"learn":[0.333859051],"iteration":618,"passed_time":1.459925145,"remaining_time":0.8985968984},
{"learn":[0.333789698],"iteration":619,"passed_time":1.461997954,"remaining_time":0.8960632619},
{"learn":[0.3336191216],"iteration":620,"passed_time":1.463927439,"remaining_time":0.8934436382},
{"learn":[0.3335757135],"iteration":621,"passed_time":1.466300818,"remaining_time":0.8910959958},
{"learn":[0.3334963088],"iteration":622,"passed_time":1.469088032,"remaining_time":0.888998697},
{"learn":[0.3334498188],"iteration":623,"passed_time":1.471336185,"remaining_time":0.8865743677},
{"learn":[0.3332711034],"iteration":624,"passed_time":1.473518571,"remaining_time":0.8841111424},
{"learn":[0.333116595],"iteration":625,"passed_time":1.475669078,"remaining_time":0.8816297688},
{"learn":[0.3329743185],"iteration":626,"passed_time":1.477786331,"remaining_time":0.8791296672},
{"learn":[0.3327527505],"iteration":627,"passed_time":1.479986817,"remaining_time":0.8766800892},
{"learn":[0.3326585973],"iteration":628,"passed_time":1.482125393,"remaining_time":0.8741947865},
{"learn":[0.3325271],"iteration":629,"passed_time":1.485332953,"remaining_time":0.8723384008},
{"learn":[0.3323413153],"iteration":630,"passed_time":1.487633475,"remaining_time":0.8699473093},
{"learn":[0.3322774935],"iteration":631,"passed_time":1.489641933,"remaining_time":0.867386442},
{"learn":[0.3321360657],"iteration":632,"passed_time":1.491703816,"remaining_time":0.8648582945},
{"learn":[0.3320004217],"iteration":633,"passed_time":1.493955649,"remaining_time":0.8624412734},
{"learn":[0.331953486],"iteration":634,"passed_time":1.49612326,"remaining_time":0.8599763621},
{"learn":[0.3318589129],"iteration":635,"passed_time":1.498727059,"remaining_time":0.8577620277},
{"learn":[0.3317441552],"iteration":636,"passed_time":1.501096285,"remaining_time":0.8554127968},
{"learn":[0.331549068],"iteration":637,"passed_time":1.503427924,"remaining_time":0.8530421765},
{"learn":[0.3315157166],"iteration":638,"passed_time":1.505766837,"remaining_time":0.8506757874},
{"learn":[0.331472387],"iteration":639,"passed_time":1.507886087,"remaining_time":0.8481859241},
{"learn":[0.3313816391],"iteration":640,"passed_time":1.510008974,"remaining_time":0.8456992535},
{"learn":[0.3313098417],"iteration":641,"passed_time":1.512063827,"remaining_time":0.843175779},
{"learn":[0.3312226192],"iteration":642,"passed_time":1.514488935,"remaining_time":0.8408593311},
{"learn":[0.3310859494],"iteration":643,"passed_time":1.517065698,"remaining_time":0.8386263797},
{"learn":[0.3309263944],"iteration":644,"passed_time":1.519145616,"remaining_time":0.836118905},
{"learn":[0.3307818915],"iteration":645,"passed_time":1.521289422,"remaining_time":0.8336477636},
{"learn":[0.3306803679],"iteration":646,"passed_time":1.523463328,"remaining_time":0.8311940566},
{"learn":[0.3306708253],"iteration":647,"passed_time":1.524714161,"remaining_time":0.8282397912},
{"learn":[0.3305082044],"iteration":648,"passed_time":1.526828195,"remaining_time":0.8257576219},
{"learn":[0.3304469499],"iteration":649,"passed_time":1.529176095,"remaining_time":0.8234025127},
{"learn":[0.3304013872],"iteration":650,"passed_time":1.531968246,"remaining_time":0.8212855879},
{"learn":[0.3303695313],"iteration":651,"passed_time":1.534069243,"remaining_time":0.8187976943},
{"learn":[0.3302292761],"iteration":652,"passed_time":1.536234723,"remaining_time":0.8163452508},
{"learn":[0.3300781377],"iteration":653,"passed_time":1.538347283,"remaining_time":0.8138656878},
{"learn":[0.3299006425],"iteration":654,"passed_time":1.54065289,"remaining_time":0.8114889266},
{"learn":[0.3297664426],"iteration":655,"passed_time":1.543078882,"remaining_time":0.8091755114},
{"learn":[0.3296107663],"iteration":656,"passed_time":1.546241663,"remaining_time":0.8072464087},
{"learn":[0.3293425975],"iteration":657,"passed_time":1.548873084,"remaining_time":0.8050373781},
{"learn":[0.3291733439],"iteration":658,"passed_time":1.551242014,"remaining_time":0.8026912393},
{"learn":[0.3290964082],"iteration":659,"passed_time":1.553603692,"remaining_time":0.8003412958},
{"learn":[0.3289685718],"iteration":660,"passed_time":1.556032526,"remaining_time":0.7980257583},
{"learn":[0.3288459081],"iteration":661,"passed_time":1.558466281,"remaining_time":0.7957123912},
{"learn":[0.3287139189],"iteration":662,"passed_time":1.560952059,"remaining_time":0.7934251041},
{"learn":[0.3286985762],"iteration":663,"passed_time":1.563499163,"remaining_time":0.7911682514},
{"learn":[0.3285636787],"iteration":664,"passed_time":1.565641656,"remaining_time":0.7887066988},
{"learn":[0.3285312539],"iteration":665,"passed_time":1.567199505,"remaining_time":0.785952905},
{"learn":[0.3284471393],"iteration":666,"passed_time":1.569318956,"remaining_time":0.783483077},
{"learn":[0.328253354],"iteration":667,"passed_time":1.571494966,"remaining_time":0.7810424084},
{"learn":[0.3280336487],"iteration":668,"passed_time":1.573630933,"remaining_time":0.7785827187},
{"learn":[0.3278318105],"iteration":669,"passed_time":1.575847144,"remaining_time":0.7761635186},
{"learn":[0.3277997406],"iteration":670,"passed_time":1.577840784,"remaining_time":0.7736357944},
{"learn":[0.3276791156],"iteration":671,"passed_time":1.580205512,"remaining_time":0.7712907858},
{"learn":[0.3275658699],"iteration":672,"passed_time":1.582374969,"remaining_time":0.7688508394},
{"learn":[0.3274035355],"iteration":673,"passed_time":1.584559696,"remaining_time":0.7664190816},
{"learn":[0.3273395188],"iteration":674,"passed_time":1.586908501,"remaining_time":0.7640670562},
{"learn":[0.3273153673],"iteration":675,"passed_time":1.588918724,"remaining_time":0.7615527614},
{"learn":[0.3271705933],"iteration":676,"passed_time":1.591279246,"remaining_time":0.7592070849},
{"learn":[0.3270720884],"iteration":677,"passed_time":1.594356016,"remaining_time":0.7572015298},
{"learn":[0.3270592089],"iteration":678,"passed_time":1.595662914,"remaining_time":0.7543561052},
{"learn":[0.3270378623],"iteration":679,"passed_time":1.597889906,"remaining_time":0.7519481912},
{"learn":[0.3268863106],"iteration":680,"passed_time":1.600079575,"remaining_time":0.7495233251},
{"learn":[0.3266281006],"iteration":681,"passed_time":1.602219604,"remaining_time":0.7470760029},
{"learn":[0.3265052055],"iteration":682,"passed_time":1.604391021,"remaining_time":0.744644149},
{"learn":[0.3264086518],"iteration":683,"passed_time":1.606503278,"remaining_time":0.7421857252},
{"learn":[0.326328285],"iteration":684,"passed_time":1.608490472,"remaining_time":0.7396708009},
{"learn":[0.3262600337],"iteration":685,"passed_time":1.610788746,"remaining_time":0.7372998049},
{"learn":[0.3261250863],"iteration":686,"passed_time":1.613187541,"remaining_time":0.7349748188},
{"learn":[0.3258787049],"iteration":687,"passed_time":1.615265462,"remaining_time":0.7325041051},
{"learn":[0.3257987753],"iteration":688,"passed_time":1.617284371,"remaining_time":0.7300078948},
{"learn":[0.3257359828],"iteration":689,"passed_time":1.619353877,"remaining_time":0.7275357997},
{"learn":[0.3255900429],"iteration":690,"passed_time":1.621381761,"remaining_time":0.7250462578},
{"learn":[0.3255085384],"iteration":691,"passed_time":1.623556251,"remaining_time":0.7226233023},
{"learn":[0.3253551219],"iteration":692,"passed_time":1.626229304,"remaining_time":0.7204219282},
{"learn":[0.3252683151],"iteration":693,"passed_time":1.628365707,"remaining_time":0.7179825738},
{"learn":[0.3251739205],"iteration":694,"passed_time":1.630554129,"remaining_time":0.71556692},
{"learn":[0.3251034016],"iteration":695,"passed_time":1.632883651,"remaining_time":0.7132135488},
{"learn":[0.3250772737],"iteration":696,"passed_time":1.634303554,"remaining_time":0.7104648161},
{"learn":[0.3249578151],"iteration":697,"passed_time":1.63649329,"remaining_time":0.7080529709},
{"learn":[0.3248670382],"iteration":698,"passed_time":1.638565169,"remaining_time":0.7055910098},
{"learn":[0.3248588021],"iteration":699,"passed_time":1.64025123,"remaining_time":0.7029648127},
{"learn":[0.3247970431],"iteration":700,"passed_time":1.642560554,"remaining_time":0.7006071407},
{"learn":[0.3246109124],"iteration":701,"passed_time":1.644557089,"remaining_time":0.698116827},
{"learn":[0.3244664406],"iteration":702,"passed_time":1.64652961,"remaining_time":0.6956177725},
{"learn":[0.3243923458],"iteration":703,"passed_time":1.648445499,"remaining_time":0.6930964028},
{"learn":[0.3242868657],"iteration":704,"passed_time":1.650491445,"remaining_time":0.6906311719},
{"learn":[0.3242326723],"iteration":705,"passed_time":1.652501791,"remaining_time":0.688152304},
{"learn":[0.324116949],"iteration":706,"passed_time":1.654426183,"remaining_time":0.6856391395},
{"learn":[0.3238900433],"iteration":707,"passed_time":1.657166109,"remaining_time":0.6834639885},
{"learn":[0.3236751049],"iteration":708,"passed_time":1.659549998,"remaining_time":0.6811411133},
{"learn":[0.3236159048],"iteration":709,"passed_time":1.661592219,"remaining_time":0.678678512},
{"learn":[0.3234902156],"iteration":710,"passed_time":1.663620755,"remaining_time":0.6762115306},
{"learn":[0.3234721493],"iteration":711,"passed_time":1.664996375,"remaining_time":0.6734816797},
{"learn":[0.3233286895],"iteration":712,"passed_time":1.667152235,"remaining_time":0.6710696936},
{"learn":[0.3232306575],"iteration":713,"passed_time":1.669298859,"remaining_time":0.6686547252},
{"learn":[0.3229074358],"iteration":714,"passed_time":1.671793973,"remaining_time":0.6663794159},
{"learn":[0.322764103],"iteration":715,"passed_time":1.674298632,"remaining_time":0.6641072785},
{"learn":[0.3226705527],"iteration":716,"passed_time":1.676493055,"remaining_time":0.6617120426},
{"learn":[0.3225747806],"iteration":717,"passed_time":1.678677715,"remaining_time":0.6593135315},
{"learn":[0.3225308417],"iteration":718,"passed_time":1.680726042,"remaining_time":0.6568623334},
{"learn":[0.3223939772],"iteration":719,"passed_time":1.682644681,"remaining_time":0.6543618205},
{"learn":[0.3223510745],"iteration":720,"passed_time":1.684691488,"remaining_time":0.6519125174},
{"learn":[0.3221299669],"iteration":721,"passed_time":1.686962587,"remaining_time":0.6495506915},
{"learn":[0.3220888134],"iteration":722,"passed_time":1.689591513,"remaining_time":0.6473262091},
{"learn":[0.3219617995],"iteration":723,"passed_time":1.691638707,"remaining_time":0.6448788439},
{"learn":[0.321951794],"iteration":724,"passed_time":1.693078068,"remaining_time":0.6422020256},
{"learn":[0.3219074295],"iteration":725,"passed_time":1.695052692,"remaining_time":0.6397306302},
{"learn":[0.3218293977],"iteration":726,"passed_time":1.697237838,"remaining_time":0.637339656},
{"learn":[0.3216593234],"iteration":727,"passed_time":1.699251346,"remaining_time":0.6348851182},
{"learn":[0.321651654],"iteration":728,"passed_time":1.700570106,"remaining_time":0.6321735238},
{"learn":[0.3215908645],"iteration":729,"passed_time":1.702514693,"remaining_time":0.6296972153},
{"learn":[0.3215379912],"iteration":730,"passed_time":1.705207506,"remaining_time":0.6274977006},
{"learn":[0.3214599123],"iteration":731,"passed_time":1.707512254,"remaining_time":0.6251547596},
{"learn":[0.3213796809],"iteration":732,"passed_time":1.70960258,"remaining_time":0.6227338182},
{"learn":[0.3213058465],"iteration":733,"passed_time":1.711731353,"remaining_time":0.620327711},
{"learn":[0.3212115392],"iteration":734,"passed_time":1.713730857,"remaining_time":0.6178757512},
{"learn":[0.3210658086],"iteration":735,"passed_time":1.715786354,"remaining_time":0.6154451054},
{"learn":[0.320949427],"iteration":736,"passed_time":1.717692781,"remaining_time":0.6129622815},
{"learn":[0.3207898779],"iteration":737,"passed_time":1.720300298,"remaining_time":0.6107299161},
{"learn":[0.3206545657],"iteration":738,"passed_time":1.722414938,"remaining_time":0.6083224612},
{"learn":[0.3205520071],"iteration":739,"passed_time":1.724057466,"remaining_time":0.6057499205},
{"learn":[0.3204858899],"iteration":740,"passed_time":1.726075302,"remaining_time":0.6033110706},
{"learn":[0.3203908948],"iteration":741,"passed_time":1.728110002,"remaining_time":0.600879219},
{"learn":[0.3202187237],"iteration":742,"passed_time":1.730074056,"remaining_time":0.5984240004},
{"learn":[0.3201027439],"iteration":743,"passed_time":1.732104,"remaining_time":0.5959927741},
{"learn":[0.3199722573],"iteration":744,"passed_time":1.73404985,"remaining_time":0.5935338411},
{"learn":[0.3198787388],"iteration":745,"passed_time":1.736895117,"remaining_time":0.5913825196},
{"learn":[0.3197917318],"iteration":746,"passed_time":1.738971153,"remaining_time":0.5889688108},
{"learn":[0.3195345731],"iteration":747,"passed_time":1.740990493,"remaining_time":0.5865369041},
{"learn":[0.3194986546],"iteration":748,"passed_time":1.743067454,"remaining_time":0.5841254085},
{"learn":[0.3193680248],"iteration":749,"passed_time":1.745125716,"remaining_time":0.5817085721},
{"learn":[0.3192542319],"iteration":750,"passed_time":1.747217661,"remaining_time":0.5793038585},
{"learn":[0.3191788156],"iteration":751,"passed_time":1.749194053,"remaining_time":0.5768618685},
{"learn":[0.3190858773],"iteration":752,"passed_time":1.751441348,"remaining_time":0.5745099775},
{"learn":[0.3190651372],"iteration":753,"passed_time":1.75340601,"remaining_time":0.5720661519},
{"learn":[0.3189585598],"iteration":754,"passed_time":1.755463959,"remaining_time":0.5696538676},
{"learn":[0.3188625633],"iteration":755,"passed_time":1.757526613,"remaining_time":0.5672440392},
{"learn":[0.3187740281],"iteration":756,"passed_time":1.759509317,"remaining_time":0.5648094639},
{"learn":[0.3185870496],"iteration":757,"passed_time":1.76161538,"remaining_time":0.5624154644},
{"learn":[0.3185068524],"iteration":758,"passed_time":1.763743124,"remaining_time":0.5600291079},
{"learn":[0.3183409871],"iteration":759,"passed_time":1.766048077,"remaining_time":0.5576993926},
{"learn":[0.3181419014],"iteration":760,"passed_time":1.768606561,"remaining_time":0.5554493666},
{"learn":[0.3180990432],"iteration":761,"passed_time":1.770302776,"remaining_time":0.5529292134},
{"learn":[0.3179645347],"iteration":762,"passed_time":1.772424079,"remaining_time":0.5505432592},
{"learn":[0.3178044762],"iteration":763,"passed_time":1.774677611,"remaining_time":0.5481988432},
{"learn":[0.3177647293],"iteration":764,"passed_time":1.776866797,"remaining_time":0.5458348985},
{"learn":[0.3177301659],"iteration":765,"passed_time":1.779054002,"remaining_time":0.5434708049},
{"learn":[0.317607991],"iteration":766,"passed_time":1.781219056,"remaining_time":0.5411004434},
{"learn":[0.3175168404],"iteration":767,"passed_time":1.783774202,"remaining_time":0.538848457},
{"learn":[0.317317676],"iteration":768,"passed_time":1.786111303,"remaining_time":0.5365301832},
{"learn":[0.3171236599],"iteration":769,"passed_time":1.788283149,"remaining_time":0.5341624991},
{"learn":[0.3169834805],"iteration":770,"passed_time":1.790426137,"remaining_time":0.5317867516},
{"learn":[0.3169241567],"iteration":771,"passed_time":1.792426596,"remaining_time":0.5293695129},
{"learn":[0.3167541086],"iteration":772,"passed_time":1.794549521,"remaining_time":0.5269893161},
{"learn":[0.3165319693],"iteration":773,"passed_time":1.796631233,"remaining_time":0.5245977501},
{"learn":[0.3163391425],"iteration":774,"passed_time":1.799050549,"remaining_time":0.5223049981},
{"learn":[0.3163100564],"iteration":775,"passed_time":1.80126088,"remaining_time":0.5199515941},
{"learn":[0.3162359579],"iteration":776,"passed_time":1.803455119,"remaining_time":0.5175939402},
{"learn":[0.3160413215],"iteration":777,"passed_time":1.80563984,"remaining_time":0.5152339904},
{"learn":[0.3158089325],"iteration":778,"passed_time":1.807948453,"remaining_time":0.5129096381},
{"learn":[0.3156596289],"iteration":779,"passed_time":1.810090718,"remaining_time":0.5105384076},
{"learn":[0.3155778594],"iteration":780,"passed_time":1.812279692,"remaining_time":0.5081808611},
{"learn":[0.3155057803],"iteration":781,"passed_time":1.814511489,"remaining_time":0.5058356835},
{"learn":[0.3153683671],"iteration":782,"passed_time":1.81708799,"remaining_time":0.5035863266},
{"learn":[0.3151056693],"iteration":783,"passed_time":1.819244819,"remaining_time":0.5012205114},
{"learn":[0.3149657018],"iteration":784,"passed_time":1.821366589,"remaining_time":0.4988456262},
{"learn":[0.3148665289],"iteration":785,"passed_time":1.823447334,"remaining_time":0.4964602157},
{"learn":[0.3148307053],"iteration":786,"passed_time":1.825087903,"remaining_time":0.4939564463},
{"learn":[0.3148257739],"iteration":787,"passed_time":1.826317018,"remaining_time":0.4913441724},
{"learn":[0.3147652064],"iteration":788,"passed_time":1.828250037,"remaining_time":0.4889236473},
{"learn":[0.3145342775],"iteration":789,"passed_time":1.830730474,"remaining_time":0.4866498729},
{"learn":[0.3145045859],"iteration":790,"passed_time":1.832952108,"remaining_time":0.4843071943},
{"learn":[0.314262715],"iteration":791,"passed_time":1.835094129,"remaining_time":0.4819439127},
{"learn":[0.3140649591],"iteration":792,"passed_time":1.837335741,"remaining_time":0.4796071859},
{"learn":[0.314031782],"iteration":793,"passed_time":1.839700457,"remaining_time":0.4773026374},
{"learn":[0.3139614938],"iteration":794,"passed_time":1.841963909,"remaining_time":0.4749718255},
{"learn":[0.3139082236],"iteration":795,"passed_time":1.844119204,"remaining_time":0.4726134643},
{"learn":[0.3138503863],"iteration":796,"passed_time":1.846655679,"remaining_time":0.4703527013},
{"learn":[0.3137669474],"iteration":797,"passed_time":1.849066124,"remaining_time":0.4680593446},
{"learn":[0.3137455934],"iteration":798,"passed_time":1.851266073,"remaining_time":0.4657127417},
{"learn":[0.3134942496],"iteration":799,"passed_time":1.853544903,"remaining_time":0.4633862258},
{"learn":[0.313413378],"iteration":800,"passed_time":1.855634851,"remaining_time":0.4610129031},
{"learn":[0.3133491676],"iteration":801,"passed_time":1.857674558,"remaining_time":0.4586278834},
{"learn":[0.3131895675],"iteration":802,"passed_time":1.859730809,"remaining_time":0.4562477824},
{"learn":[0.3131032073],"iteration":803,"passed_time":1.861940921,"remaining_time":0.4539059956},
{"learn":[0.3130601173],"iteration":804,"passed_time":1.864236635,"remaining_time":0.4515852719},
{"learn":[0.3129437484],"iteration":805,"passed_time":1.866312267,"remaining_time":0.4492116375},
{"learn":[0.3128589497],"iteration":806,"passed_time":1.868366085,"remaining_time":0.4468335247},
{"learn":[0.3127549908],"iteration":807,"passed_time":1.870519764,"remaining_time":0.4444799439},
{"learn":[0.3126872331],"iteration":808,"passed_time":1.872653488,"remaining_time":0.4421221462},
{"learn":[0.3125264646],"iteration":809,"passed_time":1.874754343,"remaining_time":0.4397571915},
{"learn":[0.312458112],"iteration":810,"passed_time":1.876807393,"remaining_time":0.4373817475},
{"learn":[0.3124440074],"iteration":811,"passed_time":1.879375553,"remaining_time":0.4351263596},
{"learn":[0.3123262331],"iteration":812,"passed_time":1.881654664,"remaining_time":0.4328037173},
{"learn":[0.3121494294],"iteration":813,"passed_time":1.883640386,"remaining_time":0.4304141423},
{"learn":[0.3120645555],"iteration":814,"passed_time":1.886061612,"remaining_time":0.4281244149},
{"learn":[0.3119762682],"iteration":815,"passed_time":1.888358853,"remaining_time":0.4258064079},
{"learn":[0.3119135361],"iteration":816,"passed_time":1.890562765,"remaining_time":0.4234675472},
{"learn":[0.3116720896],"iteration":817,"passed_time":1.892775164,"remaining_time":0.4211309045},
{"learn":[0.3115480075],"iteration":818,"passed_time":1.895548194,"remaining_time":0.4189184653},
{"learn":[0.3114187071],"iteration":819,"passed_time":1.897821526,"remaining_time":0.4165949692},
{"learn":[0.3112843861],"iteration":820,"passed_time":1.900018564,"remaining_time":0.414254961},
{"learn":[0.3112046289],"iteration":821,"passed_time":1.90220939,"remaining_time":0.4119139555},
{"learn":[0.3109624239],"iteration":822,"passed_time":1.904572524,"remaining_time":0.4096103727},
{"learn":[0.3108172177],"iteration":823,"passed_time":1.90681317,"remaining_time":0.407280483},
{"learn":[0.31073629],"iteration":824,"passed_time":1.909292685,"remaining_time":0.4050014787},
{"learn":[0.3106896868],"iteration":825,"passed_time":1.911983321,"remaining_time":0.4027664624},
{"learn":[0.3106245644],"iteration":826,"passed_time":1.914219817,"remaining_time":0.4004353425},
{"learn":[0.3106197619],"iteration":827,"passed_time":1.915833463,"remaining_time":0.3979750671},
{"learn":[0.3105877756],"iteration":828,"passed_time":1.917854009,"remaining_time":0.3956007667},
{"learn":[0.3103253803],"iteration":829,"passed_time":1.920161634,"remaining_time":0.3932861177},
{"learn":[0.3102066006],"iteration":830,"passed_time":1.922381369,"remaining_time":0.3909536117},
{"learn":[0.3100510682],"iteration":831,"passed_time":1.924548494,"remaining_time":0.3886107535},
{"learn":[0.3098939908],"iteration":832,"passed_time":1.927143878,"remaining_time":0.3863541747},
{"learn":[0.3097672651],"iteration":833,"passed_time":1.929522393,"remaining_time":0.3840536177},
{"learn":[0.3096471954],"iteration":834,"passed_time":1.931787805,"remaining_time":0.3817305243},
{"learn":[0.309501016],"iteration":835,"passed_time":1.933934316,"remaining_time":0.3793842439},
{"learn":[0.3093886296],"iteration":836,"passed_time":1.935951613,"remaining_time":0.377013277},
{"learn":[0.3093366381],"iteration":837,"passed_time":1.938007037,"remaining_time":0.374650525},
{"learn":[0.3092976306],"iteration":838,"passed_time":1.940173567,"remaining_time":0.3723098264},
{"learn":[0.3091722415],"iteration":839,"passed_time":1.943226279,"remaining_time":0.3701383389},
{"learn":[0.3090981007],"iteration":840,"passed_time":1.945434488,"remaining_time":0.3678050935},
{"learn":[0.3090729884],"iteration":841,"passed_time":1.947606469,"remaining_time":0.3654653469},
{"learn":[0.3089535775],"iteration":842,"passed_time":1.949903505,"remaining_time":0.3631492886},
{"learn":[0.3087817096],"iteration":843,"passed_time":1.952083287,"remaining_time":0.3608116029},
{"learn":[0.3086518826],"iteration":844,"passed_time":1.954267644,"remaining_time":0.35847513},
{"learn":[0.3084753695],"iteration":845,"passed_time":1.95640107,"remaining_time":0.3561297456},
{"learn":[0.3082998608],"iteration":846,"passed_time":1.958906166,"remaining_time":0.3538519993},
{"learn":[0.3081931109],"iteration":847,"passed_time":1.961059876,"remaining_time":0.3515107326},
{"learn":[0.3080935708],"iteration":848,"passed_time":1.963306316,"remaining_time":0.3491864001},
{"learn":[0.3080482118],"iteration":849,"passed_time":1.965520388,"remaining_time":0.3468565391},
{"learn":[0.3079797148],"iteration":850,"passed_time":1.967664954,"remaining_time":0.3445147804},
{"learn":[0.3079622955],"iteration":851,"passed_time":1.969762245,"remaining_time":0.3421652727},
{"learn":[0.3077958551],"iteration":852,"passed_time":1.971831514,"remaining_time":0.339811527},
{"learn":[0.3077396101],"iteration":853,"passed_time":1.974323411,"remaining_time":0.3375307002},
{"learn":[0.3076674593],"iteration":854,"passed_time":1.976370441,"remaining_time":0.3351739344},
{"learn":[0.3076121689],"iteration":855,"passed_time":1.978400051,"remaining_time":0.3328149619},
{"learn":[0.3073823053],"iteration":856,"passed_time":1.980536453,"remaining_time":0.3304745774},
{"learn":[0.3073331716],"iteration":857,"passed_time":1.98286292,"remaining_time":0.3281661243},
{"learn":[0.3071981528],"iteration":858,"passed_time":1.98500272,"remaining_time":0.325826989},
{"learn":[0.3069386652],"iteration":859,"passed_time":1.987044033,"remaining_time":0.3234722844},
{"learn":[0.3067499003],"iteration":860,"passed_time":1.989419238,"remaining_time":0.3211722114},
{"learn":[0.3067142696],"iteration":861,"passed_time":1.991595092,"remaining_time":0.3188400495},
{"learn":[0.3065252181],"iteration":862,"passed_time":1.993699127,"remaining_time":0.3164968487},
{"learn":[0.3064287161],"iteration":863,"passed_time":1.995840814,"remaining_time":0.3141601281},
{"learn":[0.3063686457],"iteration":864,"passed_time":1.997921074,"remaining_time":0.3118142717},
{"learn":[0.3063572311],"iteration":865,"passed_time":1.999405811,"remaining_time":0.3093768807},
{"learn":[0.3062009578],"iteration":866,"passed_time":2.001505782,"remaining_time":0.3070360657},
{"learn":[0.3061831217],"iteration":867,"passed_time":2.003362581,"remaining_time":0.3046588257},
{"learn":[0.3061155935],"iteration":868,"passed_time":2.006019468,"remaining_time":0.302403395},
{"learn":[0.3060377671],"iteration":869,"passed_time":2.00817815,"remaining_time":0.3000725971},
{"learn":[0.305982834],"iteration":870,"passed_time":2.010299849,"remaining_time":0.297736717},
{"learn":[0.3058110569],"iteration":871,"passed_time":2.012386911,"remaining_time":0.2953962438},
{"learn":[0.3057365405],"iteration":872,"passed_time":2.014372734,"remaining_time":0.2930416233},
{"learn":[0.3056919482],"iteration":873,"passed_time":2.016530399,"remaining_time":0.2907126205},
{"learn":[0.3056569802],"iteration":874,"passed_time":2.018620305,"remaining_time":0.2883743293},
{"learn":[0.305605093],"iteration":875,"passed_time":2.02218898,"remaining_time":0.2862459287},
{"learn":[0.305500489],"iteration":876,"passed_time":2.024547524,"remaining_time":0.2839445216},
{"learn":[0.3054213718],"iteration":877,"passed_time":2.026769849,"remaining_time":0.2816240565},
{"learn":[0.3051965866],"iteration":878,"passed_time":2.02887835,"remaining_time":0.279288146},
{"learn":[0.3051229742],"iteration":879,"passed_time":2.030943048,"remaining_time":0.2769467793},
{"learn":[0.304962259],"iteration":880,"passed_time":2.032959958,"remaining_time":0.2745995857},
{"learn":[0.3048439983],"iteration":881,"passed_time":2.034876231,"remaining_time":0.2722396771},
{"learn":[0.3047322291],"iteration":882,"passed_time":2.037567616,"remaining_time":0.269983478},
{"learn":[0.3045941025],"iteration":883,"passed_time":2.039618412,"remaining_time":0.2676422351},
{"learn":[0.3045122168],"iteration":884,"passed_time":2.041627869,"remaining_time":0.2652962767},
{"learn":[0.3044803391],"iteration":885,"passed_time":2.043598742,"remaining_time":0.2629461135},
{"learn":[0.3044356315],"iteration":886,"passed_time":2.045613895,"remaining_time":0.2606024466},
{"learn":[0.3043427841],"iteration":887,"passed_time":2.04770385,"remaining_time":0.258268954},
{"learn":[0.304284572],"iteration":888,"passed_time":2.049677745,"remaining_time":0.2559215183},
{"learn":[0.3040844392],"iteration":889,"passed_time":2.051824648,"remaining_time":0.2535963048},
{"learn":[0.3038784466],"iteration":890,"passed_time":2.054313434,"remaining_time":0.2513133157},
{"learn":[0.3037607973],"iteration":891,"passed_time":2.056211085,"remaining_time":0.2489582927},
{"learn":[0.3035720601],"iteration":892,"passed_time":2.058143591,"remaining_time":0.2466084705},
{"learn":[0.303523051],"iteration":893,"passed_time":2.060068623,"remaining_time":0.2442586957},
{"learn":[0.3034641969],"iteration":894,"passed_time":2.061869944,"remaining_time":0.2418953566},
{"learn":[0.3033507288],"iteration":895,"passed_time":2.06369062,"remaining_time":0.2395355183},
{"learn":[0.3031274184],"iteration":896,"passed_time":2.065544106,"remaining_time":0.2371806499},
{"learn":[0.3030823274],"iteration":897,"passed_time":2.067974,"remaining_time":0.2348923697},
{"learn":[0.3030177813],"iteration":898,"passed_time":2.070397319,"remaining_time":0.2326030358},
{"learn":[0.3029056725],"iteration":899,"passed_time":2.072304181,"remaining_time":0.2302560201},
{"learn":[0.3029019275],"iteration":900,"passed_time":2.073655922,"remaining_time":0.2278489859},
{"learn":[0.3028225636],"iteration":901,"passed_time":2.075648864,"remaining_time":0.2255139563},
{"learn":[0.3027104301],"iteration":902,"passed_time":2.077720161,"remaining_time":0.2231881015},
{"learn":[0.3026202594],"iteration":903,"passed_time":2.079701848,"remaining_time":0.2208532936},
{"learn":[0.3025281327],"iteration":904,"passed_time":2.081787726,"remaining_time":0.2185302033},
{"learn":[0.3022810141],"iteration":905,"passed_time":2.084584273,"remaining_time":0.2162813705},
{"learn":[0.3021814475],"iteration":906,"passed_time":2.086688505,"remaining_time":0.2139603429},
{"learn":[0.3020486142],"iteration":907,"passed_time":2.088539967,"remaining_time":0.2116141817},
{"learn":[0.3019426607],"iteration":908,"passed_time":2.090467842,"remaining_time":0.2092767587},
{"learn":[0.3018302514],"iteration":909,"passed_time":2.09237307,"remaining_time":0.2069379959},
{"learn":[0.3017229355],"iteration":910,"passed_time":2.09436975,"remaining_time":0.2046091193},
{"learn":[0.3016241071],"iteration":911,"passed_time":2.096427507,"remaining_time":0.2022868647},
{"learn":[0.3014990797],"iteration":912,"passed_time":2.098372526,"remaining_time":0.1999544466},
{"learn":[0.3014271927],"iteration":913,"passed_time":2.101033632,"remaining_time":0.1976902542},
{"learn":[0.3012373404],"iteration":914,"passed_time":2.103100053,"remaining_time":0.1953699503},
{"learn":[0.3011166874],"iteration":915,"passed_time":2.105258587,"remaining_time":0.1930586477},
{"learn":[0.3009478665],"iteration":916,"passed_time":2.107339699,"remaining_time":0.1907406707},
{"learn":[0.3008121329],"iteration":917,"passed_time":2.109376688,"remaining_time":0.1884192684},
{"learn":[0.3006197867],"iteration":918,"passed_time":2.111527682,"remaining_time":0.1861085334},
{"learn":[0.3004186182],"iteration":919,"passed_time":2.113595022,"remaining_time":0.1837908715},
{"learn":[0.3004006639],"iteration":920,"passed_time":2.116233743,"remaining_time":0.1815227641},
{"learn":[0.3002712515],"iteration":921,"passed_time":2.118510099,"remaining_time":0.1792231971},
{"learn":[0.30021391],"iteration":922,"passed_time":2.120487791,"remaining_time":0.1768987648},
{"learn":[0.3001788325],"iteration":923,"passed_time":2.122626774,"remaining_time":0.1745883494},
{"learn":[0.3001348507],"iteration":924,"passed_time":2.124744248,"remaining_time":0.1722765607},
{"learn":[0.3000896747],"iteration":925,"passed_time":2.126790968,"remaining_time":0.1699595374},
{"learn":[0.3000501334],"iteration":926,"passed_time":2.128794155,"remaining_time":0.1676396691},
{"learn":[0.299984877],"iteration":927,"passed_time":2.131229465,"remaining_time":0.1653540102},
{"learn":[0.2997585444],"iteration":928,"passed_time":2.133706233,"remaining_time":0.1630711975},
{"learn":[0.2996888703],"iteration":929,"passed_time":2.135559938,"remaining_time":0.1607410706},
{"learn":[0.2995104247],"iteration":930,"passed_time":2.137648512,"remaining_time":0.1584293741},
{"learn":[0.299357264],"iteration":931,"passed_time":2.139646137,"remaining_time":0.1561115208},
{"learn":[0.299225442],"iteration":932,"passed_time":2.141689322,"remaining_time":0.1537976255},
{"learn":[0.2991341787],"iteration":933,"passed_time":2.14358469,"remaining_time":0.1514738646},
{"learn":[0.2990650174],"iteration":934,"passed_time":2.145580469,"remaining_time":0.1491580006},
{"learn":[0.2990303937],"iteration":935,"passed_time":2.148602021,"remaining_time":0.1469129587},
{"learn":[0.298963342],"iteration":936,"passed_time":2.150839413,"remaining_time":0.1446135358},
{"learn":[0.2989433536],"iteration":937,"passed_time":2.153085086,"remaining_time":0.1423147925},
{"learn":[0.2988854452],"iteration":938,"passed_time":2.155204424,"remaining_time":0.1400079551},
{"learn":[0.2988095036],"iteration":939,"passed_time":2.15732523,"remaining_time":0.1377016104},
{"learn":[0.2985540838],"iteration":940,"passed_time":2.159462112,"remaining_time":0.135396668},
{"learn":[0.298293237],"iteration":941,"passed_time":2.161512021,"remaining_time":0.1330867274},
{"learn":[0.2982029179],"iteration":942,"passed_time":2.164483209,"remaining_time":0.1308330254},
{"learn":[0.2981712312],"iteration":943,"passed_time":2.166620282,"remaining_time":0.1285283218},
{"learn":[0.298137469],"iteration":944,"passed_time":2.168288587,"remaining_time":0.1261966902},
{"learn":[0.2980369564],"iteration":945,"passed_time":2.170376207,"remaining_time":0.1238903966},
{"learn":[0.2979179041],"iteration":946,"passed_time":2.172491006,"remaining_time":0.1215860859},
{"learn":[0.2977675621],"iteration":947,"passed_time":2.174739698,"remaining_time":0.1192895193},
{"learn":[0.2976887825],"iteration":948,"passed_time":2.176843664,"remaining_time":0.1169852759},
{"learn":[0.2976549906],"iteration":949,"passed_time":2.180086836,"remaining_time":0.1147414124},
{"learn":[0.2975452151],"iteration":950,"passed_time":2.182343643,"remaining_time":0.1124446251},
{"learn":[0.297459432],"iteration":951,"passed_time":2.184473783,"remaining_time":0.1101415353},
{"learn":[0.2974003332],"iteration":952,"passed_time":2.186544804,"remaining_time":0.1078358928},
{"learn":[0.2973492962],"iteration":953,"passed_time":2.188675886,"remaining_time":0.1055336381},
{"learn":[0.2972927438],"iteration":954,"passed_time":2.190697837,"remaining_time":0.1032265996},
{"learn":[0.2972350666],"iteration":955,"passed_time":2.192927918,"remaining_time":0.1009297368},
{"learn":[0.297076498],"iteration":956,"passed_time":2.195511911,"remaining_time":0.09864891555},
{"learn":[0.2970277801],"iteration":957,"passed_time":2.197839574,"remaining_time":0.09635622348},
{"learn":[0.2969457263],"iteration":958,"passed_time":2.20026808,"remaining_time":0.09406776985},
{"learn":[0.2968430681],"iteration":959,"passed_time":2.202367982,"remaining_time":0.09176533259},
{"learn":[0.2967838091],"iteration":960,"passed_time":2.204402137,"remaining_time":0.08946064864},
{"learn":[0.2966884784],"iteration":961,"passed_time":2.206560537,"remaining_time":0.08716143492},
{"learn":[0.2965802343],"iteration":962,"passed_time":2.208686345,"remaining_time":0.08486126143},
{"learn":[0.296471673],"iteration":963,"passed_time":2.211419278,"remaining_time":0.08258412243},
{"learn":[0.2963812249],"iteration":964,"passed_time":2.213584258,"remaining_time":0.08028543939},
{"learn":[0.2963410446],"iteration":965,"passed_time":2.215555905,"remaining_time":0.07798022855},
{"learn":[0.2962629098],"iteration":966,"passed_time":2.217542219,"remaining_time":0.0756762081},
{"learn":[0.2962257924],"iteration":967,"passed_time":2.21957237,"remaining_time":0.07337429322},
{"learn":[0.2962199287],"iteration":968,"passed_time":2.220870071,"remaining_time":0.07104950692},
{"learn":[0.2960866658],"iteration":969,"passed_time":2.222883285,"remaining_time":0.06874896757},
{"learn":[0.2959814395],"iteration":970,"passed_time":2.224873849,"remaining_time":0.06644834358},
{"learn":[0.2958232111],"iteration":971,"passed_time":2.227631224,"remaining_time":0.0641704468},
{"learn":[0.2957561706],"iteration":972,"passed_time":2.229720627,"remaining_time":0.06187302871},
{"learn":[0.2956929446],"iteration":973,"passed_time":2.231908139,"remaining_time":0.05957865668},
{"learn":[0.2956473326],"iteration":974,"passed_time":2.233991766,"remaining_time":0.05728184017},
{"learn":[0.2955175998],"iteration":975,"passed_time":2.236103158,"remaining_time":0.05498614322},
{"learn":[0.2954729148],"iteration":976,"passed_time":2.238310352,"remaining_time":0.05269307891},
{"learn":[0.2953487174],"iteration":977,"passed_time":2.240430582,"remaining_time":0.05039823395},
{"learn":[0.295118911],"iteration":978,"passed_time":2.243330799,"remaining_time":0.04812047679},
{"learn":[0.2950661894],"iteration":979,"passed_time":2.24548265,"remaining_time":0.04582617653},
{"learn":[0.2949329665],"iteration":980,"passed_time":2.247648336,"remaining_time":0.04353243465},
{"learn":[0.2948060372],"iteration":981,"passed_time":2.249732329,"remaining_time":0.04123745614},
{"learn":[0.2947450446],"iteration":982,"passed_time":2.251865982,"remaining_time":0.03894376572},
{"learn":[0.2947131573],"iteration":983,"passed_time":2.253977254,"remaining_time":0.03665003666},
{"learn":[0.2945599342],"iteration":984,"passed_time":2.256184194,"remaining_time":0.03435813493},
{"learn":[0.2943291272],"iteration":985,"passed_time":2.259084711,"remaining_time":0.03207625351},
{"learn":[0.2941745661],"iteration":986,"passed_time":2.26139005,"remaining_time":0.02978527928},
{"learn":[0.2941273687],"iteration":987,"passed_time":2.26344628,"remaining_time":0.02749125037},
{"learn":[0.2940591525],"iteration":988,"passed_time":2.265638934,"remaining_time":0.02519921969},
{"learn":[0.2939894705],"iteration":989,"passed_time":2.267834697,"remaining_time":0.02290742118},
{"learn":[0.2938546449],"iteration":990,"passed_time":2.270018202,"remaining_time":0.02061570516},
{"learn":[0.2938061671],"iteration":991,"passed_time":2.27217655,"remaining_time":0.01832400444},
{"learn":[0.2937244156],"iteration":992,"passed_time":2.275801385,"remaining_time":0.01604291006},
{"learn":[0.2936046576],"iteration":993,"passed_time":2.278242811,"remaining_time":0.01375196868},
{"learn":[0.2934436017],"iteration":994,"passed_time":2.280255247,"remaining_time":0.01145856908},
{"learn":[0.293407617],"iteration":995,"passed_time":2.282283086,"remaining_time":0.009165795527},
{"learn":[0.2933700687],"iteration":996,"passed_time":2.284213602,"remaining_time":0.006873260587},
{"learn":[0.2932392105],"iteration":997,"passed_time":2.286262381,"remaining_time":0.004581688138},
{"learn":[0.2929847446],"iteration":998,"passed_time":2.28840645,"remaining_time":0.002290697147},
{"learn":[0.2928505739],"iteration":999,"passed_time":2.290959735,"remaining_time":0}
]}